rtl/register.v


`timescale 1ns / 1ps

module register(
    input clk,
    input reset,
    input signed [15:0] d,
    output reg signed [15:0] q
);
    always @(posedge clk) begin
        if (reset) q <= 0;
        else q <= d;
    end
endmodule

rtl/mac.v
// Multiply Accumulate Unit

`timescale 1ns / 1ps

module mac(
    input [7:0] in,
    input signed [7:0] w,
    input signed [15:0] b,
    output signed [15:0] out
    );

/*
    The {1'b0, in} zero-extends in to 9 bits so it stays positive when treated as signed. Without that, values >= 128 would be interpreted as negative.

*/
wire signed [15:0] d;
assign d = $signed({1'b0, in}) * w;
assign out = d + b;
 
endmodule

rtl/shift.v
`timescale 1ns / 1ps

// Shifts data by a fixed depth.
// Optimize in future by finding a way to create 2-d arrays

module shift
(
  input clk,
  input [15:0] data_in,
  output [15:0] data_out
);

// Depth = D = n-k; for now assume n to be 5
parameter D = 29;

// Define holding register for each bit
reg [D-1:0] hr_0; reg [D-1:0] hr_1; reg [D-1:0] hr_2; reg [D-1:0] hr_3;
reg [D-1:0] hr_4; reg [D-1:0] hr_5; reg [D-1:0] hr_6; reg [D-1:0] hr_7;
reg [D-1:0] hr_8; reg [D-1:0] hr_9; reg [D-1:0] hr_10; reg [D-1:0] hr_11;
reg [D-1:0] hr_12; reg [D-1:0] hr_13; reg [D-1:0] hr_14; reg [D-1:0] hr_15;

always @ (posedge clk) begin
    hr_0 [D-1:0] <= {hr_0[D-2:0], data_in[0]};
    hr_1 [D-1:0] <= {hr_1[D-2:0], data_in[1]};
    hr_2 [D-1:0] <= {hr_2[D-2:0], data_in[2]};
    hr_3 [D-1:0] <= {hr_3[D-2:0], data_in[3]};
    hr_4 [D-1:0] <= {hr_4[D-2:0], data_in[4]};
    hr_5 [D-1:0] <= {hr_5[D-2:0], data_in[5]};
    hr_6 [D-1:0] <= {hr_6[D-2:0], data_in[6]};
    hr_7 [D-1:0] <= {hr_7[D-2:0], data_in[7]};
    hr_8 [D-1:0] <= {hr_8[D-2:0], data_in[8]};
    hr_9 [D-1:0] <= {hr_9[D-2:0], data_in[9]};
    hr_10 [D-1:0] <= {hr_10[D-2:0], data_in[10]};
    hr_11 [D-1:0] <= {hr_11[D-2:0], data_in[11]};
    hr_12 [D-1:0] <= {hr_12[D-2:0], data_in[12]};
    hr_13 [D-1:0] <= {hr_13[D-2:0], data_in[13]};
    hr_14 [D-1:0] <= {hr_14[D-2:0], data_in[14]};
    hr_15 [D-1:0] <= {hr_15[D-2:0], data_in[15]};
end

assign data_out[0] = hr_0[D-1]; assign data_out[1] = hr_1[D-1];
assign data_out[2] = hr_2[D-1]; assign data_out[3] = hr_3[D-1];
assign data_out[4] = hr_4[D-1]; assign data_out[5] = hr_5[D-1];
assign data_out[6] = hr_6[D-1]; assign data_out[7] = hr_7[D-1];
assign data_out[8] = hr_8[D-1]; assign data_out[9] = hr_9[D-1];
assign data_out[10] = hr_10[D-1]; assign data_out[11] = hr_11[D-1];
assign data_out[12] = hr_12[D-1]; assign data_out[13] = hr_13[D-1];
assign data_out[14] = hr_14[D-1]; assign data_out[15] = hr_15[D-1];

endmodule

rtl/conv.v
`timescale 1ns / 1ps
/*

Inputs clock, reset, pixel_in

13 Ouputs

*/
module conv(
    input clk,
    input reset,
    input [7:0] pxl_in,
			
	output signed [15:0] reg_00, output signed [15:0] reg_01, output signed [15:0] reg_02, output signed [15:0] sr_0,
	output signed [15:0] reg_10, output signed [15:0] reg_11, output signed [15:0] reg_12, output signed [15:0] sr_1,
	output signed [15:0] reg_20, output signed [15:0] reg_21, output signed [15:0] reg_22,
	output signed [15:0] pxl_out,	
	output valid
);

// MODULE BODY

	//Define constants
	parameter N = 5;	//Image columns
	parameter M = 5;	//Image rows
	parameter K = 3; 	//Kernel size

	// Kernel weights — override per instance for Gx vs Gy
	parameter signed [7:0] K_00 = 1,  K_01 = 2,  K_02 = 1;
	parameter signed [7:0] K_10 = 0,  K_11 = 0,  K_12 = 0;
	parameter signed [7:0] K_20 = -1, K_21 = -2, K_22 = -1;

	initial begin
		$display("[%m] Kernel:");
		$display("  %0d  %0d  %0d", K_00, K_01, K_02);
		$display("  %0d  %0d  %0d", K_10, K_11, K_12);
		$display("  %0d  %0d  %0d", K_20, K_21, K_22);
	end

	// Intermediate wires
	wire signed [15:0] wire_00; wire signed [15:0] wire_01; wire signed [15:0] wire_02;
	wire signed [15:0] wire_10; wire signed [15:0] wire_11; wire signed [15:0] wire_12;
	wire signed [15:0] wire_20; wire signed [15:0] wire_21; wire signed [15:0] wire_22;

	// Row : 1
	mac mac_00(pxl_in, K_00, 0, wire_00);
	register r_00(clk, reset, wire_00, reg_00);

	mac mac_01(pxl_in, K_01, reg_00, wire_01);
	register r_01(clk, reset, wire_01, reg_01);

	mac mac_02(pxl_in, K_02, reg_01, wire_02);
	register r_02(clk, reset, wire_02, reg_02);

	shift row_1(clk, reset, reg_02, sr_0);

	// Row : 2
	mac mac_10(pxl_in, K_10, sr_0, wire_10);
	register r_10(clk, reset, wire_10, reg_10);

	mac mac_11(pxl_in, K_11, reg_10, wire_11);
	register r_11(clk, reset, wire_11, reg_11);

	mac mac_12(pxl_in, K_12, reg_11, wire_12);
	register r_12(clk, reset, wire_12, reg_12);

	shift row_2(clk, reset, reg_12, sr_1);

	// Row : 3
	mac mac_20(pxl_in, K_20, sr_1, wire_20);
	register r_20(clk, reset, wire_20, reg_20);

	mac mac_21(pxl_in, K_21, reg_20, wire_21);
	register r_21(clk, reset, wire_21, reg_21);

	mac mac_22(pxl_in, K_22, reg_21, wire_22);
	register r_22(clk, reset, wire_22, reg_22);

	assign pxl_out = reg_22;	

	// Valid bit logic

	reg [10:0] counter = 0;
	reg temp = 0;
  localparam LATENCY = 1;

	always @(posedge clk) begin
		counter <= counter + 1;

		// The logic below needs some revisiting to scale properly
		if (counter > ((K-1)*N + (K-1) + LATENCY) && counter < (M*N) + (K-1) + LATENCY) begin
			if ((counter - (K-1) - LATENCY ) % N > 1) begin
				temp <= 1;
				end
			else
				temp <= 0;
				end
		else
			temp <= 0; 
			end
					
	assign valid = temp;

	always @(posedge clk) begin
		if (valid)
			$display("[%m] pxl_in = %0d, pxl_out = %0d", pxl_in, pxl_out);
	end

endmodule

sim/img_conv_test.v
`timescale 1ns / 1ps

module img_conv_test;

    // Original image dimensions
    parameter IMG_W = 32;
    parameter IMG_H = 32;

    // Padded dimensions fed to conv (1 zero pixel per side)
    parameter PAD_W = IMG_W + 2;
    parameter PAD_H = IMG_H + 2;

    parameter TOTAL = IMG_W * IMG_H;

    // Pixel memory: loaded from binary text file
    reg [7:0] pixel_mem [0:TOTAL-1];

    // DUT signals
    reg        clk;
    reg        reset;
    reg  [7:0] pxl_in;

    wire [15:0] reg_00; wire [15:0] reg_01; wire [15:0] reg_02; wire [15:0] sr_0;
    wire [15:0] reg_10; wire [15:0] reg_11; wire [15:0] reg_12; wire [15:0] sr_1;
    wire [15:0] reg_20; wire [15:0] reg_21; wire [15:0] reg_22;
    wire [15:0] pxl_out;
    wire        valid;

    // Conv sees the padded image so valid output is IMG_W x IMG_H
    conv #(.N(PAD_W), .M(PAD_H)) uut (
        .clk(clk),
        .reset(reset),
        .pxl_in(pxl_in),
        .reg_00(reg_00), .reg_01(reg_01), .reg_02(reg_02), .sr_0(sr_0),
        .reg_10(reg_10), .reg_11(reg_11), .reg_12(reg_12), .sr_1(sr_1),
        .reg_20(reg_20), .reg_21(reg_21), .reg_22(reg_22),
        .pxl_out(pxl_out),
        .valid(valid)
    );

    // 1.5 ns half-period → 3 ns clock (333 MHz)
    always #1.5 clk = ~clk;

    integer i, row, col;
    integer fd;

    // Write pxl_out to file whenever valid is high
    always @(posedge clk) begin
        if (valid)
            $fdisplay(fd, "%0d", pxl_out);
    end

    initial begin
        clk   = 0;
        reset = 1;
        pxl_in = 0;
        fd = $fopen("sobel_out.txt", "w");

        $readmemb("pixels.txt", pixel_mem);

        $monitor("t=%0t pxl_in=%0d | pxl_out=%0d valid=%b",
                 $time, pxl_in, pxl_out, valid);

        @(posedge clk); #0.1;
        @(posedge clk); #0.1;
        reset = 0;

        // Top padding row
        for (i = 0; i < PAD_W; i = i + 1) begin
            pxl_in = 0; @(posedge clk); #0.1;
        end

        // Each image row with 1 zero of left/right padding
        for (row = 0; row < IMG_H; row = row + 1) begin
            pxl_in = 0; @(posedge clk); #0.1;
            for (col = 0; col < IMG_W; col = col + 1) begin
                pxl_in = pixel_mem[row * IMG_W + col];
                @(posedge clk); #0.1;
            end
            pxl_in = 0; @(posedge clk); #0.1;
        end

        // Bottom padding row
        for (i = 0; i < PAD_W; i = i + 1) begin
            pxl_in = 0; @(posedge clk); #0.1;
        end

        pxl_in = 0;
        repeat (PAD_W + 4) @(posedge clk);

        $fclose(fd);
        $finish;
    end

    // Waveform dumps
    initial begin
        $dumpfile("img_conv.vcd");
        $dumpvars(0, img_conv_test);
    end

endmodule

sim/img_conv.vcd
$date
	Wed May 20 22:26:19 2026
$end

$version
	Synopsys VCS version W-2024.09-SP2-5_Full64
$end

$timescale
	1ps
$end

$comment Csum: 1 0fee285cc8ddf110 $end


$scope module img_conv_test $end
$var reg 1 ! clk $end
$var reg 1 " reset $end
$var reg 8 # pxl_in [7:0] $end
$var wire 16 $ reg_00 [15:0] $end
$var wire 16 % reg_01 [15:0] $end
$var wire 16 & reg_02 [15:0] $end
$var wire 16 ' sr_0 [15:0] $end
$var wire 16 ( reg_10 [15:0] $end
$var wire 16 ) reg_11 [15:0] $end
$var wire 16 * reg_12 [15:0] $end
$var wire 16 + sr_1 [15:0] $end
$var wire 16 , reg_20 [15:0] $end
$var wire 16 - reg_21 [15:0] $end
$var wire 16 . reg_22 [15:0] $end
$var wire 16 / pxl_out [15:0] $end
$var wire 1 0 valid $end
$var integer 32 1 i $end
$var integer 32 2 row $end
$var integer 32 3 col $end
$var integer 32 4 fd $end

$scope module uut $end
$var wire 1 ! clk $end
$var wire 1 " reset $end
$var wire 8 # pxl_in [7:0] $end
$var wire 16 $ reg_00 [15:0] $end
$var wire 16 % reg_01 [15:0] $end
$var wire 16 & reg_02 [15:0] $end
$var wire 16 ' sr_0 [15:0] $end
$var wire 16 ( reg_10 [15:0] $end
$var wire 16 ) reg_11 [15:0] $end
$var wire 16 * reg_12 [15:0] $end
$var wire 16 + sr_1 [15:0] $end
$var wire 16 , reg_20 [15:0] $end
$var wire 16 - reg_21 [15:0] $end
$var wire 16 . reg_22 [15:0] $end
$var wire 16 . pxl_out [15:0] $end
$var wire 1 0 valid $end
$var wire 16 5 wire_00 [15:0] $end
$var wire 16 6 wire_01 [15:0] $end
$var wire 16 7 wire_02 [15:0] $end
$var wire 16 8 wire_10 [15:0] $end
$var wire 16 9 wire_11 [15:0] $end
$var wire 16 : wire_12 [15:0] $end
$var wire 16 ; wire_20 [15:0] $end
$var wire 16 < wire_21 [15:0] $end
$var wire 16 = wire_22 [15:0] $end
$var reg 11 > counter [10:0] $end
$var reg 1 0 temp $end

$scope module mac_00 $end
$var wire 8 # in [7:0] $end
$var wire 8 ? w [7:0] $end
$var wire 16 @ b [15:0] $end
$var wire 16 5 out [15:0] $end
$var wire 16 A d [15:0] $end
$upscope $end


$scope module r_00 $end
$var wire 1 B clk $end
$var wire 1 C reset $end
$var wire 16 5 d [15:0] $end
$var reg 16 D q [15:0] $end
$upscope $end


$scope module mac_01 $end
$var wire 8 # in [7:0] $end
$var wire 8 E w [7:0] $end
$var wire 16 $ b [15:0] $end
$var wire 16 6 out [15:0] $end
$var wire 16 F d [15:0] $end
$upscope $end


$scope module r_01 $end
$var wire 1 B clk $end
$var wire 1 C reset $end
$var wire 16 6 d [15:0] $end
$var reg 16 G q [15:0] $end
$upscope $end


$scope module mac_02 $end
$var wire 8 # in [7:0] $end
$var wire 8 H w [7:0] $end
$var wire 16 % b [15:0] $end
$var wire 16 7 out [15:0] $end
$var wire 16 A d [15:0] $end
$upscope $end


$scope module r_02 $end
$var wire 1 B clk $end
$var wire 1 C reset $end
$var wire 16 7 d [15:0] $end
$var reg 16 I q [15:0] $end
$upscope $end


$scope module row_1 $end
$var wire 1 B clk $end
$var wire 16 J data_in [15:0] $end
$var wire 16 ' data_out [15:0] $end
$var reg 2 K hr_0 [1:0] $end
$var reg 2 L hr_1 [1:0] $end
$var reg 2 M hr_2 [1:0] $end
$var reg 2 N hr_3 [1:0] $end
$var reg 2 O hr_4 [1:0] $end
$var reg 2 P hr_5 [1:0] $end
$var reg 2 Q hr_6 [1:0] $end
$var reg 2 R hr_7 [1:0] $end
$var reg 2 S hr_8 [1:0] $end
$var reg 2 T hr_9 [1:0] $end
$var reg 2 U hr_10 [1:0] $end
$var reg 2 V hr_11 [1:0] $end
$var reg 2 W hr_12 [1:0] $end
$var reg 2 X hr_13 [1:0] $end
$var reg 2 Y hr_14 [1:0] $end
$var reg 2 Z hr_15 [1:0] $end
$upscope $end


$scope module mac_10 $end
$var wire 8 # in [7:0] $end
$var wire 8 [ w [7:0] $end
$var wire 16 ' b [15:0] $end
$var wire 16 8 out [15:0] $end
$var wire 16 \ d [15:0] $end
$upscope $end


$scope module r_10 $end
$var wire 1 B clk $end
$var wire 1 C reset $end
$var wire 16 8 d [15:0] $end
$var reg 16 ] q [15:0] $end
$upscope $end


$scope module mac_11 $end
$var wire 8 # in [7:0] $end
$var wire 8 ^ w [7:0] $end
$var wire 16 ( b [15:0] $end
$var wire 16 9 out [15:0] $end
$var wire 16 \ d [15:0] $end
$upscope $end


$scope module r_11 $end
$var wire 1 B clk $end
$var wire 1 C reset $end
$var wire 16 9 d [15:0] $end
$var reg 16 _ q [15:0] $end
$upscope $end


$scope module mac_12 $end
$var wire 8 # in [7:0] $end
$var wire 8 ` w [7:0] $end
$var wire 16 ) b [15:0] $end
$var wire 16 : out [15:0] $end
$var wire 16 \ d [15:0] $end
$upscope $end


$scope module r_12 $end
$var wire 1 B clk $end
$var wire 1 C reset $end
$var wire 16 : d [15:0] $end
$var reg 16 a q [15:0] $end
$upscope $end


$scope module row_2 $end
$var wire 1 B clk $end
$var wire 16 b data_in [15:0] $end
$var wire 16 + data_out [15:0] $end
$var reg 2 c hr_0 [1:0] $end
$var reg 2 d hr_1 [1:0] $end
$var reg 2 e hr_2 [1:0] $end
$var reg 2 f hr_3 [1:0] $end
$var reg 2 g hr_4 [1:0] $end
$var reg 2 h hr_5 [1:0] $end
$var reg 2 i hr_6 [1:0] $end
$var reg 2 j hr_7 [1:0] $end
$var reg 2 k hr_8 [1:0] $end
$var reg 2 l hr_9 [1:0] $end
$var reg 2 m hr_10 [1:0] $end
$var reg 2 n hr_11 [1:0] $end
$var reg 2 o hr_12 [1:0] $end
$var reg 2 p hr_13 [1:0] $end
$var reg 2 q hr_14 [1:0] $end
$var reg 2 r hr_15 [1:0] $end
$upscope $end


$scope module mac_20 $end
$var wire 8 # in [7:0] $end
$var wire 8 s w [7:0] $end
$var wire 16 + b [15:0] $end
$var wire 16 ; out [15:0] $end
$var wire 16 t d [15:0] $end
$upscope $end


$scope module r_20 $end
$var wire 1 B clk $end
$var wire 1 C reset $end
$var wire 16 ; d [15:0] $end
$var reg 16 u q [15:0] $end
$upscope $end


$scope module mac_21 $end
$var wire 8 # in [7:0] $end
$var wire 8 v w [7:0] $end
$var wire 16 , b [15:0] $end
$var wire 16 < out [15:0] $end
$var wire 16 w d [15:0] $end
$upscope $end


$scope module r_21 $end
$var wire 1 B clk $end
$var wire 1 C reset $end
$var wire 16 < d [15:0] $end
$var reg 16 x q [15:0] $end
$upscope $end


$scope module mac_22 $end
$var wire 8 # in [7:0] $end
$var wire 8 y w [7:0] $end
$var wire 16 - b [15:0] $end
$var wire 16 = out [15:0] $end
$var wire 16 t d [15:0] $end
$upscope $end


$scope module r_22 $end
$var wire 1 B clk $end
$var wire 1 C reset $end
$var wire 16 = d [15:0] $end
$var reg 16 z q [15:0] $end
$upscope $end

$upscope $end

$upscope $end

$enddefinitions $end

#0
$dumpvars
0!
1"
00
bxxxxxxxxxxxxxxxxxxxxxxxxxxxxxxxx 3
b00000000000 >
b0000000000000000 A
b10000000000000000000000000000011 4
bxxxxxxxxxxxxxxxxxxxxxxxxxxxxxxxx 1
b0000000000000000 F
b0000000000000000 \
b0000000000000000 t
b0000000000000000 w
b00000000 #
bxxxxxxxxxxxxxxxx /
bxxxxxxxxxxxxxxxxxxxxxxxxxxxxxxxx 2
bxxxxxxxxxxxxxxxx $
bxxxxxxxxxxxxxxxx %
bxxxxxxxxxxxxxxxx &
bxxxxxxxxxxxxxxxx (
bxxxxxxxxxxxxxxxx )
bxxxxxxxxxxxxxxxx *
bxxxxxxxxxxxxxxxx ,
bxxxxxxxxxxxxxxxx -
bxxxxxxxxxxxxxxxx .
bxxxxxxxxxxxxxxxx D
bxxxxxxxxxxxxxxxx G
bxxxxxxxxxxxxxxxx I
bxx K
bxx L
bxx U
bxx V
bxx W
bxx X
bxx Y
bxx Z
bxx M
bxx N
bxx O
bxx P
bxx Q
bxx R
bxx S
bxx T
bxxxxxxxxxxxxxxxx ]
bxxxxxxxxxxxxxxxx _
bxxxxxxxxxxxxxxxx a
bxx c
bxx d
bxx m
bxx n
bxx o
bxx p
bxx q
bxx r
bxx e
bxx f
bxx g
bxx h
bxx i
bxx j
bxx k
bxx l
bxxxxxxxxxxxxxxxx u
bxxxxxxxxxxxxxxxx x
bxxxxxxxxxxxxxxxx z
b11111111 y
b11111110 v
b11111111 s
b00000000 `
b00000000 ^
b00000000 [
b00000001 H
b00000010 E
b0000000000000000 @
b00000001 ?
b0000000000000000 5
bxxxxxxxxxxxxxxxx 6
bxxxxxxxxxxxxxxxx 7
bxxxxxxxxxxxxxxxx '
bxxxxxxxxxxxxxxxx 8
bxxxxxxxxxxxxxxxx 9
bxxxxxxxxxxxxxxxx :
bxxxxxxxxxxxxxxxx +
bxxxxxxxxxxxxxxxx ;
bxxxxxxxxxxxxxxxx <
bxxxxxxxxxxxxxxxx =
0B
1C
bxxxxxxxxxxxxxxxx J
bxxxxxxxxxxxxxxxx b
$end
#1500
1!
1B
b00000000001 >
b0000000000000000 D
b0000000000000000 $
b0000000000000000 6
b0000000000000000 G
b0000000000000000 %
b0000000000000000 7
b0000000000000000 I
b0000000000000000 &
b0000000000000000 J
b0000000000000000 ]
b0000000000000000 (
b0000000000000000 9
b0000000000000000 _
b0000000000000000 )
b0000000000000000 :
b0000000000000000 a
b0000000000000000 *
b0000000000000000 b
b0000000000000000 u
b0000000000000000 ,
b0000000000000000 <
b0000000000000000 x
b0000000000000000 -
b0000000000000000 =
b0000000000000000 z
b0000000000000000 .
b0000000000000000 /
#3000
0!
0B
#4500
1!
1B
b00000000010 >
bx0 K
bx0 L
bx0 M
bx0 N
bx0 O
bx0 P
bx0 Q
bx0 R
bx0 S
bx0 T
bx0 U
bx0 V
bx0 W
bx0 X
bx0 Y
bx0 Z
bx0 c
bx0 d
bx0 e
bx0 f
bx0 g
bx0 h
bx0 i
bx0 j
bx0 k
bx0 l
bx0 m
bx0 n
bx0 o
bx0 p
bx0 q
bx0 r
#4600
0"
0C
b00000000000000000000000000000000 1
#6000
0!
0B
#7500
1!
1B
b00000000011 >
b00 K
b00 L
b00 M
b00 N
b00 O
b00 P
b00 Q
b00 R
b00 S
b00 T
b00 U
b00 V
b00 W
b00 X
b00 Y
b00 Z
bxxxxxxxxxxxxxxxx ]
bxxxxxxxxxxxxxxxx (
bxxxxxxxxxxxxxxxx 9
b00 c
b00 d
b00 e
b00 f
b00 g
b00 h
b00 i
b00 j
b00 k
b00 l
b00 m
b00 n
b00 o
b00 p
b00 q
b00 r
bxxxxxxxxxxxxxxxx u
bxxxxxxxxxxxxxxxx ,
bxxxxxxxxxxxxxxxx <
b0000000000000000 '
b0000000000000000 8
b0000000000000000 +
b0000000000000000 ;
#7600
b00000000000000000000000000000001 1
#9000
0!
0B
#10500
1!
1B
b00000000100 >
b0000000000000000 ]
b0000000000000000 (
b0000000000000000 9
bxxxxxxxxxxxxxxxx _
bxxxxxxxxxxxxxxxx )
bxxxxxxxxxxxxxxxx :
b0000000000000000 u
b0000000000000000 ,
b0000000000000000 <
bxxxxxxxxxxxxxxxx x
bxxxxxxxxxxxxxxxx -
bxxxxxxxxxxxxxxxx =
#10600
b00000000000000000000000000000010 1
#12000
0!
0B
#13500
1!
1B
b00000000101 >
b0000000000000000 _
b0000000000000000 )
b0000000000000000 :
bxxxxxxxxxxxxxxxx a
bxxxxxxxxxxxxxxxx *
bxxxxxxxxxxxxxxxx b
b0000000000000000 x
b0000000000000000 -
b0000000000000000 =
bxxxxxxxxxxxxxxxx z
bxxxxxxxxxxxxxxxx .
bxxxxxxxxxxxxxxxx /
#13600
b00000000000000000000000000000011 1
#15000
0!
0B
#16500
1!
1B
b00000000110 >
b0000000000000000 a
b0000000000000000 *
b0000000000000000 b
b0x c
b0x d
b0x e
b0x f
b0x g
b0x h
b0x i
b0x j
b0x k
b0x l
b0x m
b0x n
b0x o
b0x p
b0x q
b0x r
b0000000000000000 z
b0000000000000000 .
b0000000000000000 /
#16600
b00000000000000000000000000000100 1
#18000
0!
0B
#19500
1!
1B
b00000000111 >
bx0 c
bx0 d
bx0 e
bx0 f
bx0 g
bx0 h
bx0 i
bx0 j
bx0 k
bx0 l
bx0 m
bx0 n
bx0 o
bx0 p
bx0 q
bx0 r
bxxxxxxxxxxxxxxxx +
bxxxxxxxxxxxxxxxx ;
#19600
b00000000000000000000000000000101 1
#21000
0!
0B
#22500
1!
1B
b00000001000 >
b00 c
b00 d
b00 e
b00 f
b00 g
b00 h
b00 i
b00 j
b00 k
b00 l
b00 m
b00 n
b00 o
b00 p
b00 q
b00 r
bxxxxxxxxxxxxxxxx u
bxxxxxxxxxxxxxxxx ,
bxxxxxxxxxxxxxxxx <
b0000000000000000 +
b0000000000000000 ;
#22600
b00000000000000000000000000000110 1
#24000
0!
0B
#25500
1!
1B
b00000001001 >
b0000000000000000 u
b0000000000000000 ,
b0000000000000000 <
bxxxxxxxxxxxxxxxx x
bxxxxxxxxxxxxxxxx -
bxxxxxxxxxxxxxxxx =
#25600
b00000000000000000000000000000111 1
#27000
0!
0B
#28500
1!
1B
b00000001010 >
b0000000000000000 x
b0000000000000000 -
b0000000000000000 =
bxxxxxxxxxxxxxxxx z
bxxxxxxxxxxxxxxxx .
bxxxxxxxxxxxxxxxx /
#28600
b00000000000000000000000000001000 1
#30000
0!
0B
#31500
1!
1B
b00000001011 >
b0000000000000000 z
b0000000000000000 .
b0000000000000000 /
#31600
b00000000000000000000000000001001 1
#33000
0!
0B
#34500
1!
1B
b00000001100 >
#34600
b00000000000000000000000000001010 1
#36000
0!
0B
#37500
1!
1B
b00000001101 >
#37600
b00000000000000000000000000001011 1
#39000
0!
0B
#40500
1!
1B
b00000001110 >
#40600
b00000000000000000000000000001100 1
#42000
0!
0B
#43500
1!
1B
b00000001111 >
#43600
b00000000000000000000000000001101 1
#45000
0!
0B
#46500
1!
1B
b00000010000 >
#46600
b00000000000000000000000000001110 1
#48000
0!
0B
#49500
1!
1B
b00000010001 >
#49600
b00000000000000000000000000001111 1
#51000
0!
0B
#52500
1!
1B
b00000010010 >
#52600
b00000000000000000000000000010000 1
#54000
0!
0B
#55500
1!
1B
b00000010011 >
#55600
b00000000000000000000000000010001 1
#57000
0!
0B
#58500
1!
1B
b00000010100 >
#58600
b00000000000000000000000000010010 1
#60000
0!
0B
#61500
1!
1B
b00000010101 >
#61600
b00000000000000000000000000010011 1
#63000
0!
0B
#64500
1!
1B
b00000010110 >
#64600
b00000000000000000000000000010100 1
#66000
0!
0B
#67500
1!
1B
b00000010111 >
#67600
b00000000000000000000000000010101 1
#69000
0!
0B
#70500
1!
1B
b00000011000 >
#70600
b00000000000000000000000000010110 1
#72000
0!
0B
#73500
1!
1B
b00000011001 >
#73600
b00000000000000000000000000010111 1
#75000
0!
0B
#76500
1!
1B
b00000011010 >
#76600
b00000000000000000000000000011000 1
#78000
0!
0B
#79500
1!
1B
b00000011011 >
#79600
b00000000000000000000000000011001 1
#81000
0!
0B
#82500
1!
1B
b00000011100 >
#82600
b00000000000000000000000000011010 1
#84000
0!
0B
#85500
1!
1B
b00000011101 >
#85600
b00000000000000000000000000011011 1
#87000
0!
0B
#88500
1!
1B
b00000011110 >
#88600
b00000000000000000000000000011100 1
#90000
0!
0B
#91500
1!
1B
b00000011111 >
#91600
b00000000000000000000000000011101 1
#93000
0!
0B
#94500
1!
1B
b00000100000 >
#94600
b00000000000000000000000000011110 1
#96000
0!
0B
#97500
1!
1B
b00000100001 >
#97600
b00000000000000000000000000011111 1
#99000
0!
0B
#100500
1!
1B
b00000100010 >
#100600
b00000000000000000000000000100000 1
#102000
0!
0B
#103500
1!
1B
b00000100011 >
#103600
b00000000000000000000000000100001 1
#105000
0!
0B
#106500
1!
1B
b00000100100 >
#106600
b00000000000000000000000000100010 1
b00000000000000000000000000000000 2
#108000
0!
0B
#109500
1!
1B
b00000100101 >
#109600
b00000000000000000000000000000000 3
b01111111 #
b1111111100000010 w
b1111111100000010 <
b1111111110000001 t
b1111111110000001 =
b1111111110000001 ;
b0000000011111110 F
b0000000011111110 6
b0000000001111111 A
b0000000001111111 5
b0000000001111111 7
#111000
0!
0B
#112500
1!
1B
b00000100110 >
b0000000001111111 D
b0000000001111111 $
b0000000101111101 6
b0000000011111110 G
b0000000011111110 %
b0000000101111101 7
b0000000001111111 I
b0000000001111111 &
b0000000001111111 J
b1111111110000001 u
b1111111110000001 ,
b1111111010000011 <
b1111111100000010 x
b1111111100000010 -
b1111111010000011 =
b1111111110000001 z
b1111111110000001 .
b1111111110000001 /
#112600
b00000000000000000000000000000001 3
#114000
0!
0B
#115500
1!
1B
b00000100111 >
b0000000101111101 G
b0000000101111101 %
b0000000111111100 7
b0000000101111101 I
b0000000101111101 &
b0000000101111101 J
b01 K
b01 L
b01 M
b01 N
b01 O
b01 P
b01 Q
b1111111010000011 x
b1111111010000011 -
b1111111000000100 =
b1111111010000011 z
b1111111010000011 .
b1111111010000011 /
#115600
b00000000000000000000000000000010 3
b10000000 #
b1111111100000000 w
b1111111010000001 <
b1111111110000000 t
b1111111000000011 =
b1111111110000000 ;
b0000000100000000 F
b0000000101111111 6
b0000000010000000 A
b0000000010000000 5
b0000000111111101 7
#117000
0!
0B
#118500
1!
1B
b00000101000 >
b0000000010000000 D
b0000000010000000 $
b0000000110000000 6
b0000000101111111 G
b0000000101111111 %
b0000000111111111 7
b0000000111111101 I
b0000000111111101 &
b0000000111111101 J
b11 K
b10 L
b11 M
b11 N
b11 O
b11 P
b11 Q
b01 S
b1111111110000000 u
b1111111110000000 ,
b1111111010000000 <
b1111111010000001 x
b1111111010000001 -
b1111111000000001 =
b1111111000000011 z
b1111111000000011 .
b1111111000000011 /
b0000000001111111 '
b0000000001111111 8
#118600
b00000000000000000000000000000011 3
#120000
0!
0B
#121500
1!
1B
b00000101001 >
b0000000110000000 G
b0000000110000000 %
b0000001000000000 7
b0000000111111111 I
b0000000111111111 &
b0000000111111111 J
b00 L
b01 R
b11 S
b0000000001111111 ]
b0000000001111111 (
b0000000001111111 9
b1111111010000000 x
b1111111010000000 -
b1111111000000000 =
b1111111000000001 z
b1111111000000001 .
b1111111000000001 /
b0000000101111101 '
b0000000101111101 8
#121600
b00000000000000000000000000000100 3
#123000
0!
0B
#124500
1!
1B
b00000101010 >
b0000001000000000 I
b0000001000000000 &
b0000001000000000 J
b01 L
b11 R
b0000000101111101 ]
b0000000101111101 (
b0000000101111101 9
b0000000001111111 _
b0000000001111111 )
b0000000001111111 :
b1111111000000000 z
b1111111000000000 .
b1111111000000000 /
b0000000111111101 '
b0000000111111101 8
#124600
b00000000000000000000000000000101 3
b10000001 #
b1111111011111110 w
b1111111001111110 <
b1111111101111111 t
b1111110111111111 =
b1111111101111111 ;
b0000000100000010 F
b0000000110000010 6
b0000000010000001 A
b0000000010000001 5
b0000001000000001 7
#126000
0!
0B
#127500
1!
1B
b00000101011 >
b0000000010000001 D
b0000000010000001 $
b0000000110000011 6
b0000000110000010 G
b0000000110000010 %
b0000001000000011 7
b0000001000000001 I
b0000001000000001 &
b0000001000000001 J
b10 K
b10 L
b10 M
b10 N
b10 O
b10 P
b10 Q
b10 R
b10 S
b01 T
b0000000111111101 ]
b0000000111111101 (
b0000000111111101 9
b0000000101111101 _
b0000000101111101 )
b0000000101111101 :
b0000000001111111 a
b0000000001111111 *
b0000000001111111 b
b1111111101111111 u
b1111111101111111 ,
b1111111001111101 <
b1111111001111110 x
b1111111001111110 -
b1111110111111101 =
b1111110111111111 z
b1111110111111111 .
b1111110111111111 /
b0000000111111111 '
b0000000111111111 8
#127600
b00000000000000000000000000000110 3
#129000
0!
0B
#130500
1!
1B
b00000101100 >
b0000000110000011 G
b0000000110000011 %
b0000001000000100 7
b0000001000000011 I
b0000001000000011 &
b0000001000000011 J
b01 K
b00 L
b00 M
b00 N
b00 O
b00 P
b00 Q
b00 R
b00 S
b11 T
b0000000111111111 ]
b0000000111111111 (
b0000000111111111 9
b0000000111111101 _
b0000000111111101 )
b0000000111111101 :
b0000000101111101 a
b0000000101111101 *
b0000000101111101 b
b01 c
b01 d
b01 e
b01 f
b01 g
b01 h
b01 i
b1111111001111101 x
b1111111001111101 -
b1111110111111100 =
b1111110111111101 z
b1111110111111101 .
b1111110111111101 /
b0000001000000000 '
b0000001000000000 8
#130600
b00000000000000000000000000000111 3
b10000000 #
b1111111100000000 w
b1111111001111111 <
b1111111110000000 t
b1111110111111101 =
b1111111110000000 ;
b0000000100000000 F
b0000000110000001 6
b0000000010000000 A
b0000000010000000 5
b0000001000000011 7
#132000
0!
0B
