rtl/register.v


`timescale 1ns / 1ps

module register(
    input clk,
    input reset,
    input signed [15:0] d,
    output reg signed [15:0] q
);
    always @(posedge clk) begin
        if (reset) q <= 0;
        else q <= d;
    end
endmodule

rtl/mac.v
// Multiply Accumulate Unit

`timescale 1ns / 1ps

module mac(
    input [7:0] in,
    input signed [7:0] w,
    input signed [15:0] b,
    output signed [15:0] out
    );

/*
    The {1'b0, in} zero-extends in to 9 bits so it stays positive when treated as signed. Without that, values >= 128 would be interpreted as negative.

*/
wire signed [15:0] d;
assign d = $signed({1'b0, in}) * w;
assign out = d + b;
 
endmodule

rtl/shift.v
`timescale 1ns / 1ps

// Shifts data by a fixed depth.
// Optimize in future by finding a way to create 2-d arrays

module shift
(
  input clk,
  input [15:0] data_in,
  output [15:0] data_out
);

// Depth = D = n-k; for now assume n to be 5
parameter D = 29;

// Define holding register for each bit
reg [D-1:0] hr_0; reg [D-1:0] hr_1; reg [D-1:0] hr_2; reg [D-1:0] hr_3;
reg [D-1:0] hr_4; reg [D-1:0] hr_5; reg [D-1:0] hr_6; reg [D-1:0] hr_7;
reg [D-1:0] hr_8; reg [D-1:0] hr_9; reg [D-1:0] hr_10; reg [D-1:0] hr_11;
reg [D-1:0] hr_12; reg [D-1:0] hr_13; reg [D-1:0] hr_14; reg [D-1:0] hr_15;

always @ (posedge clk) begin
    hr_0 [D-1:0] <= {hr_0[D-2:0], data_in[0]};
    hr_1 [D-1:0] <= {hr_1[D-2:0], data_in[1]};
    hr_2 [D-1:0] <= {hr_2[D-2:0], data_in[2]};
    hr_3 [D-1:0] <= {hr_3[D-2:0], data_in[3]};
    hr_4 [D-1:0] <= {hr_4[D-2:0], data_in[4]};
    hr_5 [D-1:0] <= {hr_5[D-2:0], data_in[5]};
    hr_6 [D-1:0] <= {hr_6[D-2:0], data_in[6]};
    hr_7 [D-1:0] <= {hr_7[D-2:0], data_in[7]};
    hr_8 [D-1:0] <= {hr_8[D-2:0], data_in[8]};
    hr_9 [D-1:0] <= {hr_9[D-2:0], data_in[9]};
    hr_10 [D-1:0] <= {hr_10[D-2:0], data_in[10]};
    hr_11 [D-1:0] <= {hr_11[D-2:0], data_in[11]};
    hr_12 [D-1:0] <= {hr_12[D-2:0], data_in[12]};
    hr_13 [D-1:0] <= {hr_13[D-2:0], data_in[13]};
    hr_14 [D-1:0] <= {hr_14[D-2:0], data_in[14]};
    hr_15 [D-1:0] <= {hr_15[D-2:0], data_in[15]};
end

assign data_out[0] = hr_0[D-1]; assign data_out[1] = hr_1[D-1];
assign data_out[2] = hr_2[D-1]; assign data_out[3] = hr_3[D-1];
assign data_out[4] = hr_4[D-1]; assign data_out[5] = hr_5[D-1];
assign data_out[6] = hr_6[D-1]; assign data_out[7] = hr_7[D-1];
assign data_out[8] = hr_8[D-1]; assign data_out[9] = hr_9[D-1];
assign data_out[10] = hr_10[D-1]; assign data_out[11] = hr_11[D-1];
assign data_out[12] = hr_12[D-1]; assign data_out[13] = hr_13[D-1];
assign data_out[14] = hr_14[D-1]; assign data_out[15] = hr_15[D-1];

endmodule

rtl/conv.v
`timescale 1ns / 1ps

module conv(
    	input clk,
    	input reset,
    	input [7:0] pxl_in,
			
	output [15:0] reg_00, output [15:0] reg_01, output [15:0] reg_02, output[15:0] sr_0, 	
	output [15:0] reg_10, output [15:0] reg_11, output [15:0] reg_12, output[15:0] sr_1, 
	output [15:0] reg_20, output [15:0] reg_21, output [15:0] reg_22, 
    	output [15:0] pxl_out,
		
	output valid
    );

	//Define constants
	parameter N = 5;	//Image columns
	parameter M = 5;	//Image rows
	parameter K = 3; 	//Kernel size

	// Intermediate wires
	wire [15:0] wire_00; wire [15:0] wire_01; wire [15:0] wire_02;
	wire [15:0] wire_10; wire [15:0] wire_11; wire [15:0] wire_12;
	wire [15:0] wire_20; wire [15:0] wire_21; wire [15:0] wire_22;

	// 3*3 kernel
	wire [7:0] kernel_00; wire [7:0] kernel_01; wire [7:0] kernel_02;
	wire [7:0] kernel_10; wire [7:0] kernel_11; wire [7:0] kernel_12;
	wire [7:0] kernel_20; wire [7:0] kernel_21; wire [7:0] kernel_22;
	assign kernel_00 = 1; assign kernel_01 = 2; assign kernel_02 = 1;
	assign kernel_10 = 0; assign kernel_11 = 0; assign kernel_12 = 0;
	assign kernel_20 = 1; assign kernel_21 = 2; assign kernel_22 = 1;

	// Row : 1
	mac mac_00(pxl_in, kernel_00, 0, wire_00);
	register r_00(clk, reset, wire_00, reg_00); 
	
	mac mac_01(pxl_in, kernel_01, reg_00, wire_01); 
	register r_01(clk, reset, wire_01, reg_01); 

	mac mac_02(pxl_in, kernel_02, reg_01, wire_02); 
	register r_02(clk, reset, wire_02, reg_02); 

	shift #(.D(N-K)) row_1(clk, reg_02, sr_0);

	// Row : 2
	mac mac_10(pxl_in, kernel_10, sr_0, wire_10); 
	register r_10(clk, reset, wire_10, reg_10); 

	mac mac_11(pxl_in, kernel_11, reg_10, wire_11); 
	register r_11(clk, reset, wire_11, reg_11); 

	mac mac_12(pxl_in, kernel_12, reg_11, wire_12); 
	register r_12(clk, reset, wire_12, reg_12); 

	shift #(.D(N-K)) row_2(clk, reg_12, sr_1);

	// Row : 3
	mac mac_20(pxl_in, kernel_20, sr_1, wire_20); 
	register r_20(clk, reset, wire_20, reg_20); 

	mac mac_21(pxl_in, kernel_21, reg_20, wire_21); 
	register r_21(clk, reset, wire_21, reg_21); 

	mac mac_22(pxl_in, kernel_22, reg_21, wire_22); 
	register r_22(clk, reset, wire_22, reg_22); 
	
	assign pxl_out = reg_22;	

	// Valid bit logic

	reg [10:0] counter = 0;
	reg temp = 0;
  localparam LATENCY = 1;

	always @(posedge clk) begin
		counter = counter + 1;
	
		// The logic below needs some revisiting to scale properly
		if (counter > ((K-1)*N + (K-1) + LATENCY) && counter < (M*N) + (K-1) + LATENCY) begin
			if ((counter - (K-1) - LATENCY ) % N > 1) begin
				temp <= 1;
				end
			else
				temp <= 0;
				end
		else
			temp <= 0; 
			end
				 
	assign valid = temp;

endmodule

sim/img_conv_test.v
`timescale 1ns / 1ps

module img_conv_test;

    // Original image dimensions
    parameter IMG_W = 32;
    parameter IMG_H = 32;

    // Padded dimensions fed to conv (1 zero pixel per side)
    parameter PAD_W = IMG_W + 2;
    parameter PAD_H = IMG_H + 2;

    parameter TOTAL = IMG_W * IMG_H;

    // Pixel memory: loaded from binary text file
    reg [7:0] pixel_mem [0:TOTAL-1];

    // DUT signals
    reg        clk;
    reg        reset;
    reg  [7:0] pxl_in;

    wire [15:0] reg_00; wire [15:0] reg_01; wire [15:0] reg_02; wire [15:0] sr_0;
    wire [15:0] reg_10; wire [15:0] reg_11; wire [15:0] reg_12; wire [15:0] sr_1;
    wire [15:0] reg_20; wire [15:0] reg_21; wire [15:0] reg_22;
    wire [15:0] pxl_out;
    wire        valid;

    // Conv sees the padded image so valid output is IMG_W x IMG_H
    conv #(.N(PAD_W), .M(PAD_H)) uut (
        .clk(clk),
        .reset(reset),
        .pxl_in(pxl_in),
        .reg_00(reg_00), .reg_01(reg_01), .reg_02(reg_02), .sr_0(sr_0),
        .reg_10(reg_10), .reg_11(reg_11), .reg_12(reg_12), .sr_1(sr_1),
        .reg_20(reg_20), .reg_21(reg_21), .reg_22(reg_22),
        .pxl_out(pxl_out),
        .valid(valid)
    );

    // 1.5 ns half-period → 3 ns clock (333 MHz)
    always #1.5 clk = ~clk;

    integer i, row, col;
    integer fd;

    // Write pxl_out to file whenever valid is high
    always @(posedge clk) begin
        if (valid)
            $fdisplay(fd, "%0d", pxl_out);
    end

    initial begin
        clk   = 0;
        reset = 1;
        pxl_in = 0;
        fd = $fopen("sobel_out.txt", "w");

        $readmemb("pixels.txt", pixel_mem);

        $monitor("t=%0t pxl_in=%0d | pxl_out=%0d valid=%b",
                 $time, pxl_in, pxl_out, valid);

        @(posedge clk); #0.1;
        @(posedge clk); #0.1;
        reset = 0;

        // Top padding row
        for (i = 0; i < PAD_W; i = i + 1) begin
            pxl_in = 0; @(posedge clk); #0.1;
        end

        // Each image row with 1 zero of left/right padding
        for (row = 0; row < IMG_H; row = row + 1) begin
            pxl_in = 0; @(posedge clk); #0.1;
            for (col = 0; col < IMG_W; col = col + 1) begin
                pxl_in = pixel_mem[row * IMG_W + col];
                @(posedge clk); #0.1;
            end
            pxl_in = 0; @(posedge clk); #0.1;
        end

        // Bottom padding row
        for (i = 0; i < PAD_W; i = i + 1) begin
            pxl_in = 0; @(posedge clk); #0.1;
        end

        pxl_in = 0;
        repeat (PAD_W + 4) @(posedge clk);

        $fclose(fd);
        $finish;
    end

    // Waveform dumps
    initial begin
        $dumpfile("img_conv.vcd");
        $dumpvars(0, img_conv_test);
    end

endmodule

sim/img_conv.vcd
$date
	Tue May  5 22:35:53 2026
$end

$version
	Synopsys VCS version W-2024.09-SP2-5_Full64
$end

$timescale
	1ps
$end

$comment Csum: 1 0fee285cc8ddf110 $end


$scope module img_conv_test $end
$var reg 1 ! clk $end
$var reg 1 " reset $end
$var reg 8 # pxl_in [7:0] $end
$var wire 16 $ reg_00 [15:0] $end
$var wire 16 % reg_01 [15:0] $end
$var wire 16 & reg_02 [15:0] $end
$var wire 16 ' sr_0 [15:0] $end
$var wire 16 ( reg_10 [15:0] $end
$var wire 16 ) reg_11 [15:0] $end
$var wire 16 * reg_12 [15:0] $end
$var wire 16 + sr_1 [15:0] $end
$var wire 16 , reg_20 [15:0] $end
$var wire 16 - reg_21 [15:0] $end
$var wire 16 . reg_22 [15:0] $end
$var wire 16 . pxl_out [15:0] $end
$var wire 1 / valid $end
$var integer 32 0 i $end
$var integer 32 1 row $end
$var integer 32 2 col $end
$var integer 32 3 fd $end

$scope module uut $end
$var wire 1 ! clk $end
$var wire 1 " reset $end
$var wire 8 # pxl_in [7:0] $end
$var wire 16 $ reg_00 [15:0] $end
$var wire 16 % reg_01 [15:0] $end
$var wire 16 & reg_02 [15:0] $end
$var wire 16 ' sr_0 [15:0] $end
$var wire 16 ( reg_10 [15:0] $end
$var wire 16 ) reg_11 [15:0] $end
$var wire 16 * reg_12 [15:0] $end
$var wire 16 + sr_1 [15:0] $end
$var wire 16 , reg_20 [15:0] $end
$var wire 16 - reg_21 [15:0] $end
$var wire 16 . reg_22 [15:0] $end
$var wire 16 . pxl_out [15:0] $end
$var wire 1 / valid $end
$var wire 16 4 wire_00 [15:0] $end
$var wire 16 5 wire_01 [15:0] $end
$var wire 16 6 wire_02 [15:0] $end
$var wire 16 7 wire_10 [15:0] $end
$var wire 16 8 wire_11 [15:0] $end
$var wire 16 9 wire_12 [15:0] $end
$var wire 16 : wire_20 [15:0] $end
$var wire 16 ; wire_21 [15:0] $end
$var wire 16 < wire_22 [15:0] $end
$var wire 8 = kernel_00 [7:0] $end
$var wire 8 > kernel_01 [7:0] $end
$var wire 8 ? kernel_02 [7:0] $end
$var wire 8 @ kernel_10 [7:0] $end
$var wire 8 A kernel_11 [7:0] $end
$var wire 8 B kernel_12 [7:0] $end
$var wire 8 C kernel_20 [7:0] $end
$var wire 8 D kernel_21 [7:0] $end
$var wire 8 E kernel_22 [7:0] $end
$var reg 11 F counter [10:0] $end
$var reg 1 / temp $end

$scope module mac_00 $end
$var wire 8 # in [7:0] $end
$var wire 8 G w [7:0] $end
$var wire 16 H b [15:0] $end
$var wire 16 4 out [15:0] $end
$var wire 16 I d [15:0] $end
$upscope $end


$scope module r_00 $end
$var wire 1 J clk $end
$var wire 1 K reset $end
$var wire 16 4 d [15:0] $end
$var reg 16 L q [15:0] $end
$upscope $end


$scope module mac_01 $end
$var wire 8 # in [7:0] $end
$var wire 8 M w [7:0] $end
$var wire 16 $ b [15:0] $end
$var wire 16 5 out [15:0] $end
$var wire 16 N d [15:0] $end
$upscope $end


$scope module r_01 $end
$var wire 1 J clk $end
$var wire 1 K reset $end
$var wire 16 5 d [15:0] $end
$var reg 16 O q [15:0] $end
$upscope $end


$scope module mac_02 $end
$var wire 8 # in [7:0] $end
$var wire 8 P w [7:0] $end
$var wire 16 % b [15:0] $end
$var wire 16 6 out [15:0] $end
$var wire 16 I d [15:0] $end
$upscope $end


$scope module r_02 $end
$var wire 1 J clk $end
$var wire 1 K reset $end
$var wire 16 6 d [15:0] $end
$var reg 16 Q q [15:0] $end
$upscope $end


$scope module row_1 $end
$var wire 1 J clk $end
$var wire 16 & data_in [15:0] $end
$var wire 16 ' data_out [15:0] $end
$var reg 31 R hr_0 [30:0] $end
$var reg 31 S hr_1 [30:0] $end
$var reg 31 T hr_2 [30:0] $end
$var reg 31 U hr_3 [30:0] $end
$var reg 31 V hr_4 [30:0] $end
$var reg 31 W hr_5 [30:0] $end
$var reg 31 X hr_6 [30:0] $end
$var reg 31 Y hr_7 [30:0] $end
$var reg 31 Z hr_8 [30:0] $end
$var reg 31 [ hr_9 [30:0] $end
$var reg 31 \ hr_10 [30:0] $end
$var reg 31 ] hr_11 [30:0] $end
$var reg 31 ^ hr_12 [30:0] $end
$var reg 31 _ hr_13 [30:0] $end
$var reg 31 ` hr_14 [30:0] $end
$var reg 31 a hr_15 [30:0] $end
$upscope $end


$scope module mac_10 $end
$var wire 8 # in [7:0] $end
$var wire 8 b w [7:0] $end
$var wire 16 ' b [15:0] $end
$var wire 16 7 out [15:0] $end
$var wire 16 c d [15:0] $end
$upscope $end


$scope module r_10 $end
$var wire 1 J clk $end
$var wire 1 K reset $end
$var wire 16 7 d [15:0] $end
$var reg 16 d q [15:0] $end
$upscope $end


$scope module mac_11 $end
$var wire 8 # in [7:0] $end
$var wire 8 e w [7:0] $end
$var wire 16 ( b [15:0] $end
$var wire 16 8 out [15:0] $end
$var wire 16 c d [15:0] $end
$upscope $end


$scope module r_11 $end
$var wire 1 J clk $end
$var wire 1 K reset $end
$var wire 16 8 d [15:0] $end
$var reg 16 f q [15:0] $end
$upscope $end


$scope module mac_12 $end
$var wire 8 # in [7:0] $end
$var wire 8 g w [7:0] $end
$var wire 16 ) b [15:0] $end
$var wire 16 9 out [15:0] $end
$var wire 16 c d [15:0] $end
$upscope $end


$scope module r_12 $end
$var wire 1 J clk $end
$var wire 1 K reset $end
$var wire 16 9 d [15:0] $end
$var reg 16 h q [15:0] $end
$upscope $end


$scope module row_2 $end
$var wire 1 J clk $end
$var wire 16 * data_in [15:0] $end
$var wire 16 + data_out [15:0] $end
$var reg 31 i hr_0 [30:0] $end
$var reg 31 j hr_1 [30:0] $end
$var reg 31 k hr_2 [30:0] $end
$var reg 31 l hr_3 [30:0] $end
$var reg 31 m hr_4 [30:0] $end
$var reg 31 n hr_5 [30:0] $end
$var reg 31 o hr_6 [30:0] $end
$var reg 31 p hr_7 [30:0] $end
$var reg 31 q hr_8 [30:0] $end
$var reg 31 r hr_9 [30:0] $end
$var reg 31 s hr_10 [30:0] $end
$var reg 31 t hr_11 [30:0] $end
$var reg 31 u hr_12 [30:0] $end
$var reg 31 v hr_13 [30:0] $end
$var reg 31 w hr_14 [30:0] $end
$var reg 31 x hr_15 [30:0] $end
$upscope $end


$scope module mac_20 $end
$var wire 8 # in [7:0] $end
$var wire 8 y w [7:0] $end
$var wire 16 + b [15:0] $end
$var wire 16 : out [15:0] $end
$var wire 16 I d [15:0] $end
$upscope $end


$scope module r_20 $end
$var wire 1 J clk $end
$var wire 1 K reset $end
$var wire 16 : d [15:0] $end
$var reg 16 z q [15:0] $end
$upscope $end


$scope module mac_21 $end
$var wire 8 # in [7:0] $end
$var wire 8 { w [7:0] $end
$var wire 16 , b [15:0] $end
$var wire 16 ; out [15:0] $end
$var wire 16 N d [15:0] $end
$upscope $end


$scope module r_21 $end
$var wire 1 J clk $end
$var wire 1 K reset $end
$var wire 16 ; d [15:0] $end
$var reg 16 | q [15:0] $end
$upscope $end


$scope module mac_22 $end
$var wire 8 # in [7:0] $end
$var wire 8 } w [7:0] $end
$var wire 16 - b [15:0] $end
$var wire 16 < out [15:0] $end
$var wire 16 I d [15:0] $end
$upscope $end


$scope module r_22 $end
$var wire 1 J clk $end
$var wire 1 K reset $end
$var wire 16 < d [15:0] $end
$var reg 16 ~ q [15:0] $end
$upscope $end

$upscope $end

$upscope $end

$enddefinitions $end

#0
$dumpvars
0!
1"
0/
bxxxxxxxxxxxxxxxxxxxxxxxxxxxxxxxx 2
b00000000000 F
b10000000000000000000000000000011 3
bxxxxxxxxxxxxxxxxxxxxxxxxxxxxxxxx 0
b00000000 #
bxxxxxxxxxxxxxxxx $
bxxxxxxxxxxxxxxxx %
bxxxxxxxxxxxxxxxx (
bxxxxxxxxxxxxxxxx )
bxxxxxxxxxxxxxxxx ,
bxxxxxxxxxxxxxxxx -
bxxxxxxxxxxxxxxxx .
bxxxxxxxxxxxxxxxxxxxxxxxxxxxxxxxx 1
bxxxxxxxxxxxxxxxx I
bxxxxxxxxxxxxxxxx N
bxxxxxxxxxxxxxxxx c
bxxxxxxxxxxxxxxxx L
bxxxxxxxxxxxxxxxx O
bxxxxxxxxxxxxxxxx Q
bxxxxxxxxxxxxxxxxxxxxxxxxxxxxxxx R
bxxxxxxxxxxxxxxxxxxxxxxxxxxxxxxx S
bxxxxxxxxxxxxxxxxxxxxxxxxxxxxxxx \
bxxxxxxxxxxxxxxxxxxxxxxxxxxxxxxx ]
bxxxxxxxxxxxxxxxxxxxxxxxxxxxxxxx ^
bxxxxxxxxxxxxxxxxxxxxxxxxxxxxxxx _
bxxxxxxxxxxxxxxxxxxxxxxxxxxxxxxx `
bxxxxxxxxxxxxxxxxxxxxxxxxxxxxxxx a
bxxxxxxxxxxxxxxxxxxxxxxxxxxxxxxx T
bxxxxxxxxxxxxxxxxxxxxxxxxxxxxxxx U
bxxxxxxxxxxxxxxxxxxxxxxxxxxxxxxx V
bxxxxxxxxxxxxxxxxxxxxxxxxxxxxxxx W
bxxxxxxxxxxxxxxxxxxxxxxxxxxxxxxx X
bxxxxxxxxxxxxxxxxxxxxxxxxxxxxxxx Y
bxxxxxxxxxxxxxxxxxxxxxxxxxxxxxxx Z
bxxxxxxxxxxxxxxxxxxxxxxxxxxxxxxx [
bxxxxxxxxxxxxxxxx d
bxxxxxxxxxxxxxxxx f
bxxxxxxxxxxxxxxxx h
bxxxxxxxxxxxxxxxxxxxxxxxxxxxxxxx i
bxxxxxxxxxxxxxxxxxxxxxxxxxxxxxxx j
bxxxxxxxxxxxxxxxxxxxxxxxxxxxxxxx s
bxxxxxxxxxxxxxxxxxxxxxxxxxxxxxxx t
bxxxxxxxxxxxxxxxxxxxxxxxxxxxxxxx u
bxxxxxxxxxxxxxxxxxxxxxxxxxxxxxxx v
bxxxxxxxxxxxxxxxxxxxxxxxxxxxxxxx w
bxxxxxxxxxxxxxxxxxxxxxxxxxxxxxxx x
bxxxxxxxxxxxxxxxxxxxxxxxxxxxxxxx k
bxxxxxxxxxxxxxxxxxxxxxxxxxxxxxxx l
bxxxxxxxxxxxxxxxxxxxxxxxxxxxxxxx m
bxxxxxxxxxxxxxxxxxxxxxxxxxxxxxxx n
bxxxxxxxxxxxxxxxxxxxxxxxxxxxxxxx o
bxxxxxxxxxxxxxxxxxxxxxxxxxxxxxxx p
bxxxxxxxxxxxxxxxxxxxxxxxxxxxxxxx q
bxxxxxxxxxxxxxxxxxxxxxxxxxxxxxxx r
bxxxxxxxxxxxxxxxx z
bxxxxxxxxxxxxxxxx |
bxxxxxxxxxxxxxxxx ~
b00000001 }
b00000010 {
b00000001 y
b00000000 g
b00000000 e
b00000000 b
b00000001 P
b00000010 M
b0000000000000000 H
b00000001 G
b00000001 E
b00000010 D
b00000001 C
b00000000 B
b00000000 A
b00000000 @
b00000001 ?
b00000010 >
b00000001 =
b0000000000000000 4
bxxxxxxxxxxxxxxxx 5
bxxxxxxxxxxxxxxxx 6
bxxxxxxxxxxxxxxxx &
bxxxxxxxxxxxxxxxx '
bxxxxxxxxxxxxxxxx 7
bxxxxxxxxxxxxxxxx 8
bxxxxxxxxxxxxxxxx 9
bxxxxxxxxxxxxxxxx *
bxxxxxxxxxxxxxxxx +
bxxxxxxxxxxxxxxxx :
bxxxxxxxxxxxxxxxx ;
bxxxxxxxxxxxxxxxx <
0J
1K
$end
b0000000000000000 I
b0000000000000000 N
b0000000000000000 c
#10000
1!
1J
b00000000001 F
b0000000000000000 L
b0000000000000000 $
b0000000000000000 5
b0000000000000000 O
b0000000000000000 %
b0000000000000000 6
b0000000000000000 Q
b0000000000000000 &
b0000000000000000 d
b0000000000000000 (
b0000000000000000 8
b0000000000000000 f
b0000000000000000 )
b0000000000000000 9
b0000000000000000 h
b0000000000000000 *
b0000000000000000 z
b0000000000000000 ,
b0000000000000000 ;
b0000000000000000 |
b0000000000000000 -
b0000000000000000 <
b0000000000000000 ~
b0000000000000000 .
#20000
0!
0J
#30000
1!
1J
b00000000010 F
bxxxxxxxxxxxxxxxxxxxxxxxxxxxxxx0 R
bxxxxxxxxxxxxxxxxxxxxxxxxxxxxxx0 S
bxxxxxxxxxxxxxxxxxxxxxxxxxxxxxx0 T
bxxxxxxxxxxxxxxxxxxxxxxxxxxxxxx0 U
bxxxxxxxxxxxxxxxxxxxxxxxxxxxxxx0 V
bxxxxxxxxxxxxxxxxxxxxxxxxxxxxxx0 W
bxxxxxxxxxxxxxxxxxxxxxxxxxxxxxx0 X
bxxxxxxxxxxxxxxxxxxxxxxxxxxxxxx0 Y
bxxxxxxxxxxxxxxxxxxxxxxxxxxxxxx0 Z
bxxxxxxxxxxxxxxxxxxxxxxxxxxxxxx0 [
bxxxxxxxxxxxxxxxxxxxxxxxxxxxxxx0 \
bxxxxxxxxxxxxxxxxxxxxxxxxxxxxxx0 ]
bxxxxxxxxxxxxxxxxxxxxxxxxxxxxxx0 ^
bxxxxxxxxxxxxxxxxxxxxxxxxxxxxxx0 _
bxxxxxxxxxxxxxxxxxxxxxxxxxxxxxx0 `
bxxxxxxxxxxxxxxxxxxxxxxxxxxxxxx0 a
bxxxxxxxxxxxxxxxxxxxxxxxxxxxxxx0 i
bxxxxxxxxxxxxxxxxxxxxxxxxxxxxxx0 j
bxxxxxxxxxxxxxxxxxxxxxxxxxxxxxx0 k
bxxxxxxxxxxxxxxxxxxxxxxxxxxxxxx0 l
bxxxxxxxxxxxxxxxxxxxxxxxxxxxxxx0 m
bxxxxxxxxxxxxxxxxxxxxxxxxxxxxxx0 n
bxxxxxxxxxxxxxxxxxxxxxxxxxxxxxx0 o
bxxxxxxxxxxxxxxxxxxxxxxxxxxxxxx0 p
bxxxxxxxxxxxxxxxxxxxxxxxxxxxxxx0 q
bxxxxxxxxxxxxxxxxxxxxxxxxxxxxxx0 r
bxxxxxxxxxxxxxxxxxxxxxxxxxxxxxx0 s
bxxxxxxxxxxxxxxxxxxxxxxxxxxxxxx0 t
bxxxxxxxxxxxxxxxxxxxxxxxxxxxxxx0 u
bxxxxxxxxxxxxxxxxxxxxxxxxxxxxxx0 v
bxxxxxxxxxxxxxxxxxxxxxxxxxxxxxx0 w
bxxxxxxxxxxxxxxxxxxxxxxxxxxxxxx0 x
#31000
0"
0K
b00000000000000000000000000000000 0
#40000
0!
0J
#50000
1!
1J
b00000000011 F
bxxxxxxxxxxxxxxxxxxxxxxxxxxxxx00 R
bxxxxxxxxxxxxxxxxxxxxxxxxxxxxx00 S
bxxxxxxxxxxxxxxxxxxxxxxxxxxxxx00 T
bxxxxxxxxxxxxxxxxxxxxxxxxxxxxx00 U
bxxxxxxxxxxxxxxxxxxxxxxxxxxxxx00 V
bxxxxxxxxxxxxxxxxxxxxxxxxxxxxx00 W
bxxxxxxxxxxxxxxxxxxxxxxxxxxxxx00 X
bxxxxxxxxxxxxxxxxxxxxxxxxxxxxx00 Y
bxxxxxxxxxxxxxxxxxxxxxxxxxxxxx00 Z
bxxxxxxxxxxxxxxxxxxxxxxxxxxxxx00 [
bxxxxxxxxxxxxxxxxxxxxxxxxxxxxx00 \
bxxxxxxxxxxxxxxxxxxxxxxxxxxxxx00 ]
bxxxxxxxxxxxxxxxxxxxxxxxxxxxxx00 ^
bxxxxxxxxxxxxxxxxxxxxxxxxxxxxx00 _
bxxxxxxxxxxxxxxxxxxxxxxxxxxxxx00 `
bxxxxxxxxxxxxxxxxxxxxxxxxxxxxx00 a
bxxxxxxxxxxxxxxxx d
bxxxxxxxxxxxxxxxx (
bxxxxxxxxxxxxxxxx 8
bxxxxxxxxxxxxxxxxxxxxxxxxxxxxx00 i
bxxxxxxxxxxxxxxxxxxxxxxxxxxxxx00 j
bxxxxxxxxxxxxxxxxxxxxxxxxxxxxx00 k
bxxxxxxxxxxxxxxxxxxxxxxxxxxxxx00 l
bxxxxxxxxxxxxxxxxxxxxxxxxxxxxx00 m
bxxxxxxxxxxxxxxxxxxxxxxxxxxxxx00 n
bxxxxxxxxxxxxxxxxxxxxxxxxxxxxx00 o
bxxxxxxxxxxxxxxxxxxxxxxxxxxxxx00 p
bxxxxxxxxxxxxxxxxxxxxxxxxxxxxx00 q
bxxxxxxxxxxxxxxxxxxxxxxxxxxxxx00 r
bxxxxxxxxxxxxxxxxxxxxxxxxxxxxx00 s
bxxxxxxxxxxxxxxxxxxxxxxxxxxxxx00 t
bxxxxxxxxxxxxxxxxxxxxxxxxxxxxx00 u
bxxxxxxxxxxxxxxxxxxxxxxxxxxxxx00 v
bxxxxxxxxxxxxxxxxxxxxxxxxxxxxx00 w
bxxxxxxxxxxxxxxxxxxxxxxxxxxxxx00 x
bxxxxxxxxxxxxxxxx z
bxxxxxxxxxxxxxxxx ,
bxxxxxxxxxxxxxxxx ;
#51000
b00000000000000000000000000000001 0
#60000
0!
0J
#70000
1!
1J
b00000000100 F
bxxxxxxxxxxxxxxxxxxxxxxxxxxxx000 R
bxxxxxxxxxxxxxxxxxxxxxxxxxxxx000 S
bxxxxxxxxxxxxxxxxxxxxxxxxxxxx000 T
bxxxxxxxxxxxxxxxxxxxxxxxxxxxx000 U
bxxxxxxxxxxxxxxxxxxxxxxxxxxxx000 V
bxxxxxxxxxxxxxxxxxxxxxxxxxxxx000 W
bxxxxxxxxxxxxxxxxxxxxxxxxxxxx000 X
bxxxxxxxxxxxxxxxxxxxxxxxxxxxx000 Y
bxxxxxxxxxxxxxxxxxxxxxxxxxxxx000 Z
bxxxxxxxxxxxxxxxxxxxxxxxxxxxx000 [
bxxxxxxxxxxxxxxxxxxxxxxxxxxxx000 \
bxxxxxxxxxxxxxxxxxxxxxxxxxxxx000 ]
bxxxxxxxxxxxxxxxxxxxxxxxxxxxx000 ^
bxxxxxxxxxxxxxxxxxxxxxxxxxxxx000 _
bxxxxxxxxxxxxxxxxxxxxxxxxxxxx000 `
bxxxxxxxxxxxxxxxxxxxxxxxxxxxx000 a
bxxxxxxxxxxxxxxxx f
bxxxxxxxxxxxxxxxx )
bxxxxxxxxxxxxxxxx 9
bxxxxxxxxxxxxxxxxxxxxxxxxxxxx000 i
bxxxxxxxxxxxxxxxxxxxxxxxxxxxx000 j
bxxxxxxxxxxxxxxxxxxxxxxxxxxxx000 k
bxxxxxxxxxxxxxxxxxxxxxxxxxxxx000 l
bxxxxxxxxxxxxxxxxxxxxxxxxxxxx000 m
bxxxxxxxxxxxxxxxxxxxxxxxxxxxx000 n
bxxxxxxxxxxxxxxxxxxxxxxxxxxxx000 o
bxxxxxxxxxxxxxxxxxxxxxxxxxxxx000 p
bxxxxxxxxxxxxxxxxxxxxxxxxxxxx000 q
bxxxxxxxxxxxxxxxxxxxxxxxxxxxx000 r
bxxxxxxxxxxxxxxxxxxxxxxxxxxxx000 s
bxxxxxxxxxxxxxxxxxxxxxxxxxxxx000 t
bxxxxxxxxxxxxxxxxxxxxxxxxxxxx000 u
bxxxxxxxxxxxxxxxxxxxxxxxxxxxx000 v
bxxxxxxxxxxxxxxxxxxxxxxxxxxxx000 w
bxxxxxxxxxxxxxxxxxxxxxxxxxxxx000 x
bxxxxxxxxxxxxxxxx |
bxxxxxxxxxxxxxxxx -
bxxxxxxxxxxxxxxxx <
#71000
b00000000000000000000000000000010 0
#80000
0!
0J
