rtl/register.v


`timescale 1ns / 1ps

module register(
    input clk,
    input reset,
    input signed [15:0] d,
    output reg signed [15:0] q
);
    always @(posedge clk) begin
        if (reset) q <= 0;
        else q <= d;
    end
endmodule

rtl/mac.v
// Multiply Accumulate Unit

`timescale 1ns / 1ps

module mac(
    input [7:0] in,
    input signed [7:0] w,
    input signed [15:0] b,
    output signed [15:0] out
    );

/*
    The {1'b0, in} zero-extends in to 9 bits so it stays positive when treated as signed. Without that, values >= 128 would be interpreted as negative.

*/
wire signed [15:0] d;
assign d = $signed({1'b0, in}) * w;
assign out = d + b;
 
endmodule

rtl/shift.v
`timescale 1ns / 1ps

// Shifts data by a fixed depth.
// Optimize in future by finding a way to create 2-d arrays

module shift
(
  input clk,
  input [15:0] data_in,
  output [15:0] data_out
);

// Depth = D = n-k; for now assume n to be 5
parameter D = 29;

// Define holding register for each bit
reg [D-1:0] hr_0; reg [D-1:0] hr_1; reg [D-1:0] hr_2; reg [D-1:0] hr_3;
reg [D-1:0] hr_4; reg [D-1:0] hr_5; reg [D-1:0] hr_6; reg [D-1:0] hr_7;
reg [D-1:0] hr_8; reg [D-1:0] hr_9; reg [D-1:0] hr_10; reg [D-1:0] hr_11;
reg [D-1:0] hr_12; reg [D-1:0] hr_13; reg [D-1:0] hr_14; reg [D-1:0] hr_15;

always @ (posedge clk) begin
    hr_0 [D-1:0] <= {hr_0[D-2:0], data_in[0]};
    hr_1 [D-1:0] <= {hr_1[D-2:0], data_in[1]};
    hr_2 [D-1:0] <= {hr_2[D-2:0], data_in[2]};
    hr_3 [D-1:0] <= {hr_3[D-2:0], data_in[3]};
    hr_4 [D-1:0] <= {hr_4[D-2:0], data_in[4]};
    hr_5 [D-1:0] <= {hr_5[D-2:0], data_in[5]};
    hr_6 [D-1:0] <= {hr_6[D-2:0], data_in[6]};
    hr_7 [D-1:0] <= {hr_7[D-2:0], data_in[7]};
    hr_8 [D-1:0] <= {hr_8[D-2:0], data_in[8]};
    hr_9 [D-1:0] <= {hr_9[D-2:0], data_in[9]};
    hr_10 [D-1:0] <= {hr_10[D-2:0], data_in[10]};
    hr_11 [D-1:0] <= {hr_11[D-2:0], data_in[11]};
    hr_12 [D-1:0] <= {hr_12[D-2:0], data_in[12]};
    hr_13 [D-1:0] <= {hr_13[D-2:0], data_in[13]};
    hr_14 [D-1:0] <= {hr_14[D-2:0], data_in[14]};
    hr_15 [D-1:0] <= {hr_15[D-2:0], data_in[15]};
end

assign data_out[0] = hr_0[D-1]; assign data_out[1] = hr_1[D-1];
assign data_out[2] = hr_2[D-1]; assign data_out[3] = hr_3[D-1];
assign data_out[4] = hr_4[D-1]; assign data_out[5] = hr_5[D-1];
assign data_out[6] = hr_6[D-1]; assign data_out[7] = hr_7[D-1];
assign data_out[8] = hr_8[D-1]; assign data_out[9] = hr_9[D-1];
assign data_out[10] = hr_10[D-1]; assign data_out[11] = hr_11[D-1];
assign data_out[12] = hr_12[D-1]; assign data_out[13] = hr_13[D-1];
assign data_out[14] = hr_14[D-1]; assign data_out[15] = hr_15[D-1];

endmodule

rtl/conv.v
`timescale 1ns / 1ps

module conv(
    	input clk,
    	input reset,
    	input [7:0] pxl_in,
			
	output [15:0] reg_00, output [15:0] reg_01, output [15:0] reg_02, output[15:0] sr_0, 	
	output [15:0] reg_10, output [15:0] reg_11, output [15:0] reg_12, output[15:0] sr_1, 
	output [15:0] reg_20, output [15:0] reg_21, output [15:0] reg_22, 
    	output [15:0] pxl_out,
		
	output valid
    );

	//Define constants
	parameter N = 5;	//Image columns
	parameter M = 5;	//Image rows
	parameter K = 3; 	//Kernel size

	// Intermediate wires
	wire [15:0] wire_00; wire [15:0] wire_01; wire [15:0] wire_02;
	wire [15:0] wire_10; wire [15:0] wire_11; wire [15:0] wire_12;
	wire [15:0] wire_20; wire [15:0] wire_21; wire [15:0] wire_22;

	// 3*3 kernel
	wire [7:0] kernel_00; wire [7:0] kernel_01; wire [7:0] kernel_02;
	wire [7:0] kernel_10; wire [7:0] kernel_11; wire [7:0] kernel_12;
	wire [7:0] kernel_20; wire [7:0] kernel_21; wire [7:0] kernel_22;
	assign kernel_00 = 1; assign kernel_01 = 2; assign kernel_02 = 1;
	assign kernel_10 = 0; assign kernel_11 = 0; assign kernel_12 = 0;
	assign kernel_20 = 1; assign kernel_21 = 2; assign kernel_22 = 1;

	// Row : 1
	mac mac_00(pxl_in, kernel_00, 0, wire_00);
	register r_00(clk, reset, wire_00, reg_00); 
	
	mac mac_01(pxl_in, kernel_01, reg_00, wire_01); 
	register r_01(clk, reset, wire_01, reg_01); 

	mac mac_02(pxl_in, kernel_02, reg_01, wire_02); 
	register r_02(clk, reset, wire_02, reg_02); 

	shift #(.D(N-K)) row_1(clk, reg_02, sr_0);

	// Row : 2
	mac mac_10(pxl_in, kernel_10, sr_0, wire_10); 
	register r_10(clk, reset, wire_10, reg_10); 

	mac mac_11(pxl_in, kernel_11, reg_10, wire_11); 
	register r_11(clk, reset, wire_11, reg_11); 

	mac mac_12(pxl_in, kernel_12, reg_11, wire_12); 
	register r_12(clk, reset, wire_12, reg_12); 

	shift #(.D(N-K)) row_2(clk, reg_12, sr_1);

	// Row : 3
	mac mac_20(pxl_in, kernel_20, sr_1, wire_20); 
	register r_20(clk, reset, wire_20, reg_20); 

	mac mac_21(pxl_in, kernel_21, reg_20, wire_21); 
	register r_21(clk, reset, wire_21, reg_21); 

	mac mac_22(pxl_in, kernel_22, reg_21, wire_22); 
	register r_22(clk, reset, wire_22, reg_22); 
	
	assign pxl_out = reg_22;	

	// Valid bit logic

	reg [10:0] counter = 0;
	reg temp = 0;
  localparam LATENCY = 1;

	always @(posedge clk) begin
		counter = counter + 1;
	
		// The logic below needs some revisiting to scale properly
		if (counter > ((K-1)*N + (K-1) + LATENCY) && counter < (M*N) + (K-1) + LATENCY) begin
			if ((counter - (K-1) - LATENCY ) % N > 1) begin
				temp <= 1;
				end
			else
				temp <= 0;
				end
		else
			temp <= 0; 
			end
				 
	assign valid = temp;

endmodule

sim/img_conv_test.v
`timescale 1ns / 1ps

module img_conv_test;

    // Original image dimensions
    parameter IMG_W = 32;
    parameter IMG_H = 32;

    // Padded dimensions fed to conv (1 zero pixel per side)
    parameter PAD_W = IMG_W + 2;
    parameter PAD_H = IMG_H + 2;

    parameter TOTAL = IMG_W * IMG_H;

    // Pixel memory: loaded from binary text file
    reg [7:0] pixel_mem [0:TOTAL-1];

    // DUT signals
    reg        clk;
    reg        reset;
    reg  [7:0] pxl_in;

    wire [15:0] reg_00; wire [15:0] reg_01; wire [15:0] reg_02; wire [15:0] sr_0;
    wire [15:0] reg_10; wire [15:0] reg_11; wire [15:0] reg_12; wire [15:0] sr_1;
    wire [15:0] reg_20; wire [15:0] reg_21; wire [15:0] reg_22;
    wire [15:0] pxl_out;
    wire        valid;

    // Conv sees the padded image so valid output is IMG_W x IMG_H
    conv #(.N(PAD_W), .M(PAD_H)) uut (
        .clk(clk),
        .reset(reset),
        .pxl_in(pxl_in),
        .reg_00(reg_00), .reg_01(reg_01), .reg_02(reg_02), .sr_0(sr_0),
        .reg_10(reg_10), .reg_11(reg_11), .reg_12(reg_12), .sr_1(sr_1),
        .reg_20(reg_20), .reg_21(reg_21), .reg_22(reg_22),
        .pxl_out(pxl_out),
        .valid(valid)
    );

    // 1.5 ns half-period → 3 ns clock (333 MHz)
    always #1.5 clk = ~clk;

    integer i, row, col;
    integer fd;

    // Write pxl_out to file whenever valid is high
    always @(posedge clk) begin
        if (valid)
            $fdisplay(fd, "%0d", pxl_out);
    end

    initial begin
        clk   = 0;
        reset = 1;
        pxl_in = 0;
        fd = $fopen("sobel_out.txt", "w");

        $readmemb("pixels.txt", pixel_mem);

        $monitor("t=%0t pxl_in=%0d | pxl_out=%0d valid=%b",
                 $time, pxl_in, pxl_out, valid);

        @(posedge clk); #0.1;
        @(posedge clk); #0.1;
        reset = 0;

        // Top padding row
        for (i = 0; i < PAD_W; i = i + 1) begin
            pxl_in = 0; @(posedge clk); #0.1;
        end

        // Each image row with 1 zero of left/right padding
        for (row = 0; row < IMG_H; row = row + 1) begin
            pxl_in = 0; @(posedge clk); #0.1;
            for (col = 0; col < IMG_W; col = col + 1) begin
                pxl_in = pixel_mem[row * IMG_W + col];
                @(posedge clk); #0.1;
            end
            pxl_in = 0; @(posedge clk); #0.1;
        end

        // Bottom padding row
        for (i = 0; i < PAD_W; i = i + 1) begin
            pxl_in = 0; @(posedge clk); #0.1;
        end

        pxl_in = 0;
        repeat (PAD_W + 4) @(posedge clk);

        $fclose(fd);
        $finish;
    end

    // Waveform dumps
    initial begin
        $dumpfile("img_conv.vcd");
        $dumpvars(0, img_conv_test);
    end

endmodule

sim/img_conv.vcd
$date
	Tue May  5 01:35:12 2026
$end

$version
	Synopsys VCS version W-2024.09-SP2-5_Full64
$end

$timescale
	1ps
$end

$comment Csum: 1 0fee285cc8ddf110 $end


$scope module img_conv_test $end
$var reg 1 ! clk $end
$var reg 1 " reset $end
$var reg 8 # pxl_in [7:0] $end
$var wire 16 $ reg_00 [15:0] $end
$var wire 16 % reg_01 [15:0] $end
$var wire 16 & reg_02 [15:0] $end
$var wire 16 ' sr_0 [15:0] $end
$var wire 16 ( reg_10 [15:0] $end
$var wire 16 ) reg_11 [15:0] $end
$var wire 16 * reg_12 [15:0] $end
$var wire 16 + sr_1 [15:0] $end
$var wire 16 , reg_20 [15:0] $end
$var wire 16 - reg_21 [15:0] $end
$var wire 16 . reg_22 [15:0] $end
$var wire 16 . pxl_out [15:0] $end
$var wire 1 / valid $end
$var integer 32 0 i $end
$var integer 32 1 row $end
$var integer 32 2 col $end
$var integer 32 3 fd $end

$scope module uut $end
$var wire 1 ! clk $end
$var wire 1 " reset $end
$var wire 8 # pxl_in [7:0] $end
$var wire 16 $ reg_00 [15:0] $end
$var wire 16 % reg_01 [15:0] $end
$var wire 16 & reg_02 [15:0] $end
$var wire 16 ' sr_0 [15:0] $end
$var wire 16 ( reg_10 [15:0] $end
$var wire 16 ) reg_11 [15:0] $end
$var wire 16 * reg_12 [15:0] $end
$var wire 16 + sr_1 [15:0] $end
$var wire 16 , reg_20 [15:0] $end
$var wire 16 - reg_21 [15:0] $end
$var wire 16 . reg_22 [15:0] $end
$var wire 16 . pxl_out [15:0] $end
$var wire 1 / valid $end
$var wire 16 4 wire_00 [15:0] $end
$var wire 16 5 wire_01 [15:0] $end
$var wire 16 6 wire_02 [15:0] $end
$var wire 16 7 wire_10 [15:0] $end
$var wire 16 8 wire_11 [15:0] $end
$var wire 16 9 wire_12 [15:0] $end
$var wire 16 : wire_20 [15:0] $end
$var wire 16 ; wire_21 [15:0] $end
$var wire 16 < wire_22 [15:0] $end
$var wire 8 = kernel_00 [7:0] $end
$var wire 8 > kernel_01 [7:0] $end
$var wire 8 ? kernel_02 [7:0] $end
$var wire 8 @ kernel_10 [7:0] $end
$var wire 8 A kernel_11 [7:0] $end
$var wire 8 B kernel_12 [7:0] $end
$var wire 8 C kernel_20 [7:0] $end
$var wire 8 D kernel_21 [7:0] $end
$var wire 8 E kernel_22 [7:0] $end
$var reg 11 F counter [10:0] $end
$var reg 1 / temp $end

$scope module mac_00 $end
$var wire 8 # in [7:0] $end
$var wire 8 G w [7:0] $end
$var wire 16 H b [15:0] $end
$var wire 16 4 out [15:0] $end
$var wire 16 I d [15:0] $end
$upscope $end


$scope module r_00 $end
$var wire 1 J clk $end
$var wire 1 K reset $end
$var wire 16 4 d [15:0] $end
$var reg 16 L q [15:0] $end
$upscope $end


$scope module mac_01 $end
$var wire 8 # in [7:0] $end
$var wire 8 M w [7:0] $end
$var wire 16 $ b [15:0] $end
$var wire 16 5 out [15:0] $end
$var wire 16 N d [15:0] $end
$upscope $end


$scope module r_01 $end
$var wire 1 J clk $end
$var wire 1 K reset $end
$var wire 16 5 d [15:0] $end
$var reg 16 O q [15:0] $end
$upscope $end


$scope module mac_02 $end
$var wire 8 # in [7:0] $end
$var wire 8 P w [7:0] $end
$var wire 16 % b [15:0] $end
$var wire 16 6 out [15:0] $end
$var wire 16 I d [15:0] $end
$upscope $end


$scope module r_02 $end
$var wire 1 J clk $end
$var wire 1 K reset $end
$var wire 16 6 d [15:0] $end
$var reg 16 Q q [15:0] $end
$upscope $end


$scope module row_1 $end
$var wire 1 J clk $end
$var wire 16 & data_in [15:0] $end
$var wire 16 ' data_out [15:0] $end
$var reg 2 R hr_0 [1:0] $end
$var reg 2 S hr_1 [1:0] $end
$var reg 2 T hr_2 [1:0] $end
$var reg 2 U hr_3 [1:0] $end
$var reg 2 V hr_4 [1:0] $end
$var reg 2 W hr_5 [1:0] $end
$var reg 2 X hr_6 [1:0] $end
$var reg 2 Y hr_7 [1:0] $end
$var reg 2 Z hr_8 [1:0] $end
$var reg 2 [ hr_9 [1:0] $end
$var reg 2 \ hr_10 [1:0] $end
$var reg 2 ] hr_11 [1:0] $end
$var reg 2 ^ hr_12 [1:0] $end
$var reg 2 _ hr_13 [1:0] $end
$var reg 2 ` hr_14 [1:0] $end
$var reg 2 a hr_15 [1:0] $end
$upscope $end


$scope module mac_10 $end
$var wire 8 # in [7:0] $end
$var wire 8 b w [7:0] $end
$var wire 16 ' b [15:0] $end
$var wire 16 7 out [15:0] $end
$var wire 16 c d [15:0] $end
$upscope $end


$scope module r_10 $end
$var wire 1 J clk $end
$var wire 1 K reset $end
$var wire 16 7 d [15:0] $end
$var reg 16 d q [15:0] $end
$upscope $end


$scope module mac_11 $end
$var wire 8 # in [7:0] $end
$var wire 8 e w [7:0] $end
$var wire 16 ( b [15:0] $end
$var wire 16 8 out [15:0] $end
$var wire 16 c d [15:0] $end
$upscope $end


$scope module r_11 $end
$var wire 1 J clk $end
$var wire 1 K reset $end
$var wire 16 8 d [15:0] $end
$var reg 16 f q [15:0] $end
$upscope $end


$scope module mac_12 $end
$var wire 8 # in [7:0] $end
$var wire 8 g w [7:0] $end
$var wire 16 ) b [15:0] $end
$var wire 16 9 out [15:0] $end
$var wire 16 c d [15:0] $end
$upscope $end


$scope module r_12 $end
$var wire 1 J clk $end
$var wire 1 K reset $end
$var wire 16 9 d [15:0] $end
$var reg 16 h q [15:0] $end
$upscope $end


$scope module row_2 $end
$var wire 1 J clk $end
$var wire 16 * data_in [15:0] $end
$var wire 16 + data_out [15:0] $end
$var reg 2 i hr_0 [1:0] $end
$var reg 2 j hr_1 [1:0] $end
$var reg 2 k hr_2 [1:0] $end
$var reg 2 l hr_3 [1:0] $end
$var reg 2 m hr_4 [1:0] $end
$var reg 2 n hr_5 [1:0] $end
$var reg 2 o hr_6 [1:0] $end
$var reg 2 p hr_7 [1:0] $end
$var reg 2 q hr_8 [1:0] $end
$var reg 2 r hr_9 [1:0] $end
$var reg 2 s hr_10 [1:0] $end
$var reg 2 t hr_11 [1:0] $end
$var reg 2 u hr_12 [1:0] $end
$var reg 2 v hr_13 [1:0] $end
$var reg 2 w hr_14 [1:0] $end
$var reg 2 x hr_15 [1:0] $end
$upscope $end


$scope module mac_20 $end
$var wire 8 # in [7:0] $end
$var wire 8 y w [7:0] $end
$var wire 16 + b [15:0] $end
$var wire 16 : out [15:0] $end
$var wire 16 I d [15:0] $end
$upscope $end


$scope module r_20 $end
$var wire 1 J clk $end
$var wire 1 K reset $end
$var wire 16 : d [15:0] $end
$var reg 16 z q [15:0] $end
$upscope $end


$scope module mac_21 $end
$var wire 8 # in [7:0] $end
$var wire 8 { w [7:0] $end
$var wire 16 , b [15:0] $end
$var wire 16 ; out [15:0] $end
$var wire 16 N d [15:0] $end
$upscope $end


$scope module r_21 $end
$var wire 1 J clk $end
$var wire 1 K reset $end
$var wire 16 ; d [15:0] $end
$var reg 16 | q [15:0] $end
$upscope $end


$scope module mac_22 $end
$var wire 8 # in [7:0] $end
$var wire 8 } w [7:0] $end
$var wire 16 - b [15:0] $end
$var wire 16 < out [15:0] $end
$var wire 16 I d [15:0] $end
$upscope $end


$scope module r_22 $end
$var wire 1 J clk $end
$var wire 1 K reset $end
$var wire 16 < d [15:0] $end
$var reg 16 ~ q [15:0] $end
$upscope $end

$upscope $end

$upscope $end

$enddefinitions $end

#0
$dumpvars
0!
1"
0/
bxxxxxxxxxxxxxxxxxxxxxxxxxxxxxxxx 2
b00000000000 F
b10000000000000000000000000000011 3
bxxxxxxxxxxxxxxxxxxxxxxxxxxxxxxxx 0
b00000000 #
bxxxxxxxxxxxxxxxx $
bxxxxxxxxxxxxxxxx %
bxxxxxxxxxxxxxxxx (
bxxxxxxxxxxxxxxxx )
bxxxxxxxxxxxxxxxx ,
bxxxxxxxxxxxxxxxx -
bxxxxxxxxxxxxxxxx .
bxxxxxxxxxxxxxxxxxxxxxxxxxxxxxxxx 1
bxxxxxxxxxxxxxxxx I
bxxxxxxxxxxxxxxxx N
bxxxxxxxxxxxxxxxx c
bxxxxxxxxxxxxxxxx L
bxxxxxxxxxxxxxxxx O
bxxxxxxxxxxxxxxxx Q
bxx R
bxx S
bxx \
bxx ]
bxx ^
bxx _
bxx `
bxx a
bxx T
bxx U
bxx V
bxx W
bxx X
bxx Y
bxx Z
bxx [
bxxxxxxxxxxxxxxxx d
bxxxxxxxxxxxxxxxx f
bxxxxxxxxxxxxxxxx h
bxx i
bxx j
bxx s
bxx t
bxx u
bxx v
bxx w
bxx x
bxx k
bxx l
bxx m
bxx n
bxx o
bxx p
bxx q
bxx r
bxxxxxxxxxxxxxxxx z
bxxxxxxxxxxxxxxxx |
bxxxxxxxxxxxxxxxx ~
b00000001 }
b00000010 {
b00000001 y
b00000000 g
b00000000 e
b00000000 b
b00000001 P
b00000010 M
b0000000000000000 H
b00000001 G
b00000001 E
b00000010 D
b00000001 C
b00000000 B
b00000000 A
b00000000 @
b00000001 ?
b00000010 >
b00000001 =
b0000000000000000 4
bxxxxxxxxxxxxxxxx 5
bxxxxxxxxxxxxxxxx 6
bxxxxxxxxxxxxxxxx &
bxxxxxxxxxxxxxxxx '
bxxxxxxxxxxxxxxxx 7
bxxxxxxxxxxxxxxxx 8
bxxxxxxxxxxxxxxxx 9
bxxxxxxxxxxxxxxxx *
bxxxxxxxxxxxxxxxx +
bxxxxxxxxxxxxxxxx :
bxxxxxxxxxxxxxxxx ;
bxxxxxxxxxxxxxxxx <
0J
1K
$end
b0000000000000000 I
b0000000000000000 N
b0000000000000000 c
#10000
1!
1J
b00000000001 F
b0000000000000000 L
b0000000000000000 $
b0000000000000000 5
b0000000000000000 O
b0000000000000000 %
b0000000000000000 6
b0000000000000000 Q
b0000000000000000 &
b0000000000000000 d
b0000000000000000 (
b0000000000000000 8
b0000000000000000 f
b0000000000000000 )
b0000000000000000 9
b0000000000000000 h
b0000000000000000 *
b0000000000000000 z
b0000000000000000 ,
b0000000000000000 ;
b0000000000000000 |
b0000000000000000 -
b0000000000000000 <
b0000000000000000 ~
b0000000000000000 .
#20000
0!
0J
#30000
1!
1J
b00000000010 F
bx0 R
bx0 S
bx0 T
bx0 U
bx0 V
bx0 W
bx0 X
bx0 Y
bx0 Z
bx0 [
bx0 \
bx0 ]
bx0 ^
bx0 _
bx0 `
bx0 a
bx0 i
bx0 j
bx0 k
bx0 l
bx0 m
bx0 n
bx0 o
bx0 p
bx0 q
bx0 r
bx0 s
bx0 t
bx0 u
bx0 v
bx0 w
bx0 x
#31000
0"
0K
b00000000000000000000000000000000 0
#40000
0!
0J
#50000
1!
1J
b00000000011 F
b00 R
b00 S
b00 T
b00 U
b00 V
b00 W
b00 X
b00 Y
b00 Z
b00 [
b00 \
b00 ]
b00 ^
b00 _
b00 `
b00 a
bxxxxxxxxxxxxxxxx d
bxxxxxxxxxxxxxxxx (
bxxxxxxxxxxxxxxxx 8
b00 i
b00 j
b00 k
b00 l
b00 m
b00 n
b00 o
b00 p
b00 q
b00 r
b00 s
b00 t
b00 u
b00 v
b00 w
b00 x
bxxxxxxxxxxxxxxxx z
bxxxxxxxxxxxxxxxx ,
bxxxxxxxxxxxxxxxx ;
b0000000000000000 '
b0000000000000000 7
b0000000000000000 +
b0000000000000000 :
#51000
b00000000000000000000000000000001 0
#60000
0!
0J
#70000
1!
1J
b00000000100 F
b0000000000000000 d
b0000000000000000 (
b0000000000000000 8
bxxxxxxxxxxxxxxxx f
bxxxxxxxxxxxxxxxx )
bxxxxxxxxxxxxxxxx 9
b0000000000000000 z
b0000000000000000 ,
b0000000000000000 ;
bxxxxxxxxxxxxxxxx |
bxxxxxxxxxxxxxxxx -
bxxxxxxxxxxxxxxxx <
#71000
b00000000000000000000000000000010 0
#80000
0!
0J
#90000
1!
1J
b00000000101 F
b0000000000000000 f
b0000000000000000 )
b0000000000000000 9
bxxxxxxxxxxxxxxxx h
bxxxxxxxxxxxxxxxx *
b0000000000000000 |
b0000000000000000 -
b0000000000000000 <
bxxxxxxxxxxxxxxxx ~
bxxxxxxxxxxxxxxxx .
#91000
b00000000000000000000000000000011 0
#100000
0!
0J
#110000
1!
1J
b00000000110 F
b0000000000000000 h
b0000000000000000 *
b0x i
b0x j
b0x k
b0x l
b0x m
b0x n
b0x o
b0x p
b0x q
b0x r
b0x s
b0x t
b0x u
b0x v
b0x w
b0x x
b0000000000000000 ~
b0000000000000000 .
#111000
b00000000000000000000000000000100 0
#120000
0!
0J
#130000
1!
1J
b00000000111 F
bx0 i
bx0 j
bx0 k
bx0 l
bx0 m
bx0 n
bx0 o
bx0 p
bx0 q
bx0 r
bx0 s
bx0 t
bx0 u
bx0 v
bx0 w
bx0 x
bxxxxxxxxxxxxxxxx +
bxxxxxxxxxxxxxxxx :
#131000
b00000000000000000000000000000101 0
#140000
0!
0J
#150000
1!
1J
b00000001000 F
b00 i
b00 j
b00 k
b00 l
b00 m
b00 n
b00 o
b00 p
b00 q
b00 r
b00 s
b00 t
b00 u
b00 v
b00 w
b00 x
bxxxxxxxxxxxxxxxx z
bxxxxxxxxxxxxxxxx ,
bxxxxxxxxxxxxxxxx ;
b0000000000000000 +
b0000000000000000 :
#151000
b00000000000000000000000000000110 0
#160000
0!
0J
#170000
1!
1J
b00000001001 F
b0000000000000000 z
b0000000000000000 ,
b0000000000000000 ;
bxxxxxxxxxxxxxxxx |
bxxxxxxxxxxxxxxxx -
bxxxxxxxxxxxxxxxx <
#171000
b00000000000000000000000000000111 0
#180000
0!
0J
#190000
1!
1J
b00000001010 F
b0000000000000000 |
b0000000000000000 -
b0000000000000000 <
bxxxxxxxxxxxxxxxx ~
bxxxxxxxxxxxxxxxx .
#191000
b00000000000000000000000000001000 0
#200000
0!
0J
#210000
1!
1J
b00000001011 F
b0000000000000000 ~
b0000000000000000 .
#211000
b00000000000000000000000000001001 0
#220000
0!
0J
#230000
1!
1J
b00000001100 F
#231000
b00000000000000000000000000001010 0
#240000
0!
0J
#250000
1!
1J
b00000001101 F
#251000
b00000000000000000000000000001011 0
#260000
0!
0J
#270000
1!
1J
b00000001110 F
#271000
b00000000000000000000000000001100 0
#280000
0!
0J
#290000
1!
1J
b00000001111 F
#291000
b00000000000000000000000000001101 0
#300000
0!
0J
#310000
1!
1J
b00000010000 F
#311000
b00000000000000000000000000001110 0
#320000
0!
0J
#330000
1!
1J
b00000010001 F
#331000
b00000000000000000000000000001111 0
#340000
0!
0J
#350000
1!
1J
b00000010010 F
#351000
b00000000000000000000000000010000 0
#360000
0!
0J
#370000
1!
1J
b00000010011 F
#371000
b00000000000000000000000000010001 0
#380000
0!
0J
#390000
1!
1J
b00000010100 F
#391000
b00000000000000000000000000010010 0
#400000
0!
0J
#410000
1!
1J
b00000010101 F
#411000
b00000000000000000000000000010011 0
#420000
0!
0J
#430000
1!
1J
b00000010110 F
#431000
b00000000000000000000000000010100 0
#440000
0!
0J
#450000
1!
1J
b00000010111 F
#451000
b00000000000000000000000000010101 0
#460000
0!
0J
#470000
1!
1J
b00000011000 F
#471000
b00000000000000000000000000010110 0
#480000
0!
0J
#490000
1!
1J
b00000011001 F
#491000
b00000000000000000000000000010111 0
#500000
0!
0J
#510000
1!
1J
b00000011010 F
#511000
b00000000000000000000000000011000 0
#520000
0!
0J
#530000
1!
1J
b00000011011 F
#531000
b00000000000000000000000000011001 0
#540000
0!
0J
#550000
1!
1J
b00000011100 F
#551000
b00000000000000000000000000011010 0
#560000
0!
0J
#570000
1!
1J
b00000011101 F
#571000
b00000000000000000000000000011011 0
#580000
0!
0J
#590000
1!
1J
b00000011110 F
#591000
b00000000000000000000000000011100 0
#600000
0!
0J
#610000
1!
1J
b00000011111 F
#611000
b00000000000000000000000000011101 0
#620000
0!
0J
#630000
1!
1J
b00000100000 F
#631000
b00000000000000000000000000011110 0
#640000
0!
0J
#650000
1!
1J
b00000100001 F
#651000
b00000000000000000000000000011111 0
#660000
0!
0J
#670000
1!
1J
b00000100010 F
#671000
b00000000000000000000000000100000 0
#680000
0!
0J
#690000
1!
1J
b00000100011 F
#691000
b00000000000000000000000000100001 0
#700000
0!
0J
#710000
1!
1J
b00000100100 F
#711000
b00000000000000000000000000100010 0
b00000000000000000000000000000000 1
#720000
0!
0J
#730000
1!
1J
b00000100101 F
#731000
b00000000000000000000000000000000 2
#740000
0!
0J
#750000
1!
1J
b00000100110 F
#751000
b00000000000000000000000000000001 2
#760000
0!
0J
#770000
1!
1J
b00000100111 F
#771000
b00000000000000000000000000000010 2
#780000
0!
0J
#790000
1!
1J
b00000101000 F
#791000
b00000000000000000000000000000011 2
#800000
0!
0J
#810000
1!
1J
b00000101001 F
#811000
b00000000000000000000000000000100 2
#820000
0!
0J
#830000
1!
1J
b00000101010 F
#831000
b00000000000000000000000000000101 2
b00000010 #
b0000000000000010 I
b0000000000000100 N
b0000000000000010 4
b0000000000000010 <
b0000000000000010 :
b0000000000000010 6
b0000000000000100 ;
b0000000000000100 5
#840000
0!
0J
#850000
1!
1J
b00000101011 F
b0000000000000010 L
b0000000000000010 $
b0000000000000110 5
b0000000000000100 O
b0000000000000100 %
b0000000000000110 6
b0000000000000010 Q
b0000000000000010 &
b0000000000000010 z
b0000000000000010 ,
b0000000000000110 ;
b0000000000000100 |
b0000000000000100 -
b0000000000000110 <
b0000000000000010 ~
b0000000000000010 .
#851000
b00000000000000000000000000000110 2
b10010010 #
b0000000010010010 I
b0000000100100100 N
b0000000010010010 4
b0000000010010110 <
b0000000010010010 :
b0000000010010110 6
b0000000100100110 ;
b0000000100100110 5
#860000
0!
0J
#870000
1!
1J
b00000101100 F
b0000000010010010 L
b0000000010010010 $
b0000000110110110 5
b0000000100100110 O
b0000000100100110 %
b0000000110111000 6
b0000000010010110 Q
b0000000010010110 &
b01 S
b0000000010010010 z
b0000000010010010 ,
b0000000110110110 ;
b0000000100100110 |
b0000000100100110 -
b0000000110111000 <
b0000000010010110 ~
b0000000010010110 .
#871000
b00000000000000000000000000000111 2
b10011010 #
b0000000010011010 I
b0000000100110100 N
b0000000010011010 4
b0000000111000000 <
b0000000010011010 :
b0000000111000000 6
b0000000111000110 ;
b0000000111000110 5
#880000
0!
0J
#890000
1!
1J
b00000101101 F
b0000000010011010 L
b0000000010011010 $
b0000000111001110 5
b0000000111000110 O
b0000000111000110 %
b0000001001100000 6
b0000000111000000 Q
b0000000111000000 &
b11 S
b01 T
b01 V
b01 Y
b0000000010011010 z
b0000000010011010 ,
b0000000111001110 ;
b0000000111000110 |
b0000000111000110 -
b0000001001100000 <
b0000000111000000 ~
b0000000111000000 .
b0000000000000010 '
b0000000000000010 7
#891000
b00000000000000000000000000001000 2
b10010100 #
b0000000010010100 I
b0000000100101000 N
b0000000010010100 4
b0000001001011010 <
b0000000010010100 :
b0000001001011010 6
b0000000111000010 ;
b0000000111000010 5
#900000
0!
0J
#910000
1!
1J
b00000101110 F
b0000000010010100 L
b0000000010010100 $
b0000000110111100 5
b0000000111000010 O
b0000000111000010 %
b0000001001010110 6
b0000001001011010 Q
b0000001001011010 &
b10 S
b10 T
b10 V
b01 X
b11 Y
b01 Z
b0000000000000010 d
b0000000000000010 (
b0000000000000010 8
b0000000010010100 z
b0000000010010100 ,
b0000000110111100 ;
b0000000111000010 |
b0000000111000010 -
b0000001001010110 <
b0000001001011010 ~
b0000001001011010 .
b0000000010010110 '
b0000000010010110 7
#911000
b00000000000000000000000000001001 2
#920000
0!
0J
#930000
1!
1J
b00000101111 F
b0000000110111100 O
b0000000110111100 %
b0000001001010000 6
b0000001001010110 Q
b0000001001010110 &
b01 S
b00 T
b01 U
b01 V
b11 X
b10 Y
b10 Z
b01 [
b0000000010010110 d
b0000000010010110 (
b0000000010010110 8
b0000000000000010 f
b0000000000000010 )
b0000000000000010 9
b0000000110111100 |
b0000000110111100 -
b0000001001010000 <
b0000001001010110 ~
b0000001001010110 .
b0000000111000000 '
b0000000111000000 7
#931000
b00000000000000000000000000001010 2
#940000
0!
0J
#950000
1!
1J
b00000110000 F
b0000001001010000 Q
b0000001001010000 &
b11 S
b01 T
b10 U
b11 V
b00 Y
b00 Z
b11 [
b0000000111000000 d
b0000000111000000 (
b0000000111000000 8
b0000000010010110 f
b0000000010010110 )
b0000000010010110 9
b0000000000000010 h
b0000000000000010 *
b0000001001010000 ~
b0000001001010000 .
b0000001001011010 '
b0000001001011010 7
#951000
b00000000000000000000000000001011 2
#960000
0!
0J
#970000
1!
1J
b00000110001 F
b10 S
b10 T
b00 U
b0000001001011010 d
b0000001001011010 (
b0000001001011010 8
b0000000111000000 f
b0000000111000000 )
b0000000111000000 9
b0000000010010110 h
b0000000010010110 *
b01 j
b0000001001010110 '
b0000001001010110 7
#971000
b00000000000000000000000000001100 2
#980000
0!
0J
